{"uuid":"30415cea-fed3-11f0-9526-b792a0bc94a6","page":{"id":486748902,"data":{"appState":"[\"~#iR\",[\"^ \",\"n\",\"appTemplate\",\"v\",[\"^ \",\"appMaxWidth\",\"100%\",\"appStyles\",\"\",\"appTesting\",null,\"appThemeId\",null,\"appThemeModeId\",null,\"appThemeName\",null,\"createdAt\",null,\"customComponentCollections\",[],\"customDocumentTitle\",\"\",\"customDocumentTitleEnabled\",false,\"customShortcuts\",[],\"experimentalFeatures\",[\"^ \",\"disableMultiplayerEditing\",false,\"multiplayerEditingEnabled\",false,\"sourceControlTemplateDehydration\",false],\"folders\",[\"~#iL\",[]],\"formAppSettings\",[\"^ \",\"customRedirectUrl\",\"\"],\"inAppRetoolPillAppearance\",\"NO_OVERRIDE\",\"instrumentationEnabled\",false,\"internationalizationSettings\",[\"^ \",\"internationalizationEnabled\",false,\"internationalizationFiles\",[]],\"isFetching\",false,\"isFormApp\",false,\"isGlobalWidget\",false,\"isMobileApp\",false,\"loadingIndicatorsDisabled\",false,\"markdownLinkBehavior\",\"auto\",\"mobileAppSettings\",[\"^ \",\"displaySetting\",[\"^ \",\"landscapeMode\",false,\"tabletMode\",false],\"mobileOfflineModeBannerMode\",\"default\",\"mobileOfflineModeDelaySync\",false,\"mobileOfflineModeEnabled\",false],\"mobileOfflineAssets\",[],\"multiScreenMobileApp\",false,\"notificationsSettings\",[\"^ \",\"globalQueryShowFailureToast\",true,\"globalQueryShowSuccessToast\",false,\"globalQueryToastDuration\",4.5,\"globalToastPosition\",\"bottomRight\"],\"pageCodeFolders\",[\"^ \"],\"pageLoadValueOverrides\",[\"^A\",[]],\"persistUrlParams\",false,\"plugins\",[\"~#iOM\",[\"page1\",[\"^0\",[\"^ \",\"n\",\"pluginTemplate\",\"v\",[\"^ \",\"id\",\"page1\",\"uuid\",\"ce7c14a6-0f6a-477e-8dc3-0ae94cf28920\",\"_comment\",null,\"type\",\"screen\",\"subtype\",\"Screen\",\"namespace\",null,\"resourceName\",null,\"resourceDisplayName\",null,\"template\",[\"^15\",[\"title\",\"Page 1\",\"browserTitle\",\"\",\"urlSlug\",\"\",\"_order\",0,\"_searchParams\",[\"^A\",[]],\"_hashParams\",[\"^A\",[]],\"_customShortcuts\",[\"^A\",[]]]],\"style\",null,\"position2\",null,\"mobilePosition2\",null,\"mobileAppPosition\",null,\"tabIndex\",null,\"container\",\"\",\"^7\",\"~m1769884344950\",\"updatedAt\",\"~m1769884344950\",\"folder\",\"\",\"presetName\",null,\"screen\",null,\"boxId\",null,\"subBoxIds\",null]]],\"$main\",[\"^0\",[\"^ \",\"n\",\"pluginTemplate\",\"v\",[\"^ \",\"id\",\"$main\",\"^16\",null,\"^17\",null,\"^18\",\"frame\",\"^19\",\"Frame\",\"^1:\",null,\"^1;\",null,\"^1<\",null,\"^1=\",[\"~#iM\",[\"type\",\"main\",\"padding\",\"8px 12px\",\"enableFullBleed\",false,\"isHiddenOnDesktop\",false,\"isHiddenOnMobile\",false]],\"^1>\",[\"^1J\",[]],\"^1?\",null,\"^1@\",null,\"^1A\",null,\"^1B\",null,\"^1C\",\"\",\"^7\",\"~m1769884344951\",\"^1D\",\"~m1769884344951\",\"^1E\",\"\",\"^1F\",null,\"^1G\",\"page1\",\"^1H\",null,\"^1I\",null]]],\"query1\",[\"^0\",[\"^ \",\"n\",\"pluginTemplate\",\"v\",[\"^ \",\"id\",\"query1\",\"^16\",null,\"^17\",null,\"^18\",\"datasource\",\"^19\",\"GoogleSheetsQuery\",\"^1:\",null,\"^1;\",\"f859c0ad-40a4-445b-9adb-2f3808e1013f\",\"^1<\",\"Google_sheets_Tiller\",\"^1=\",[\"^1J\",[\"queryRefreshTime\",\"\",\"allowedGroupIds\",[\"^A\",[]],\"streamResponse\",false,\"lastReceivedFromResourceAt\",null,\"isFunction\",false,\"functionParameters\",null,\"queryDisabledMessage\",\"\",\"servedFromCache\",false,\"offlineUserQueryInputs\",\"\",\"functionDescription\",null,\"successMessage\",\"\",\"queryDisabled\",\"\",\"useSheetRange\",false,\"playgroundQuerySaveId\",\"latest\",\"workflowParams\",null,\"resourceNameOverride\",\"\",\"useRawSpreadsheetId\",false,\"runWhenModelUpdates\",true,\"workflowRunExecutionType\",\"sync\",\"showFailureToaster\",true,\"spreadsheetId\",\"1fokhoSVGss2ivA_8gnuDMR_IZBOvzksnArKeFHkzQWA\",\"query\",\"\",\"playgroundQueryUuid\",\"\",\"playgroundQueryId\",null,\"error\",null,\"workflowRunBodyType\",\"raw\",\"sheetUpdate\",\"\",\"privateParams\",[\"^A\",[]],\"queryRunOnSelectorUpdate\",false,\"sheetIdToCopy\",\"\",\"sheetName\",\"Transactions\",\"runWhenPageLoadsDelay\",\"\",\"doNotThrowOnDeleteNoOp\",false,\"data\",null,\"importedQueryInputs\",[\"^1J\",[]],\"isImported\",false,\"showSuccessToaster\",true,\"cacheKeyTtl\",\"\",\"filterBy\",\"\",\"requestSentTimestamp\",null,\"metadata\",null,\"queryRunTime\",null,\"actionType\",\"read\",\"changesetObject\",\"\",\"offlineOptimisticResponse\",null,\"errorTransformer\",\"return data.error\",\"finished\",null,\"confirmationMessage\",null,\"isFetching\",false,\"changeset\",\"\",\"rawData\",null,\"offset\",\"\",\"queryTriggerDelay\",\"0\",\"resourceTypeOverride\",null,\"watchedParams\",[\"^A\",[]],\"bulkUpdateRows\",\"\",\"enableErrorTransformer\",false,\"showLatestVersionUpdatedWarning\",false,\"useRawCopyToSpreadsheetId\",false,\"timestamp\",0,\"importedQueryDefaults\",[\"^1J\",[]],\"enableTransformer\",true,\"valueFormatting\",\"unformatted\",\"showUpdateSetValueDynamicallyToggle\",true,\"copyToSpreadsheetId\",\"\",\"overrideOrgCacheForUserCache\",false,\"bulkUpdatePrimaryKey\",\"\",\"runWhenPageLoads\",false,\"sheetTitle\",\"\",\"transformer\",\"return data\",\"events\",[\"^A\",[[\"^1J\",[\"method\",\"run\",\"params\",[\"^1J\",[\"src\",\"await syncToRetoolDB.trigger();\\n// Optionally run the default query after sync\\nawait queryResults.trigger();\"]],\"targetId\",null,\"pluginId\",\"\",\"waitType\",\"debounce\",\"event\",\"success\",\"type\",\"script\",\"id\",\"796345ab\",\"waitMs\",\"0\"]]]],\"queryTimeout\",\"10000\",\"workflowId\",null,\"requireConfirmation\",false,\"queryFailureConditions\",\"\",\"changesetIsObject\",false,\"limit\",\"\",\"enableCaching\",false,\"allowedGroups\",[\"^A\",[]],\"sheetRange\",\"A1:Z4000\",\"offlineQueryType\",\"None\",\"queryThrottleTime\",\"750\",\"updateSetValueDynamically\",false,\"notificationDuration\",\"\"]],\"^1>\",null,\"^1?\",null,\"^1@\",null,\"^1A\",null,\"^1B\",null,\"^1C\",\"\",\"^7\",\"~m1769884562824\",\"^1D\",\"~m1769887620315\",\"^1E\",\"\",\"^1F\",null,\"^1G\",\"page1\",\"^1H\",null,\"^1I\",null]]],\"dataTable\",[\"^0\",[\"^ \",\"n\",\"pluginTemplate\",\"v\",[\"^ \",\"id\",\"dataTable\",\"^16\",\"bee2eb06-79e8-46b5-aca7-22aeae57b83c\",\"^17\",null,\"^18\",\"widget\",\"^19\",\"TableWidget2\",\"^1:\",null,\"^1;\",null,\"^1<\",null,\"^1=\",[\"^1J\",[\"selectedRowKey\",null,\"_nextAfterCursor\",\"\",\"_columnBackgroundColor\",[\"^1J\",[\"5b197\",\"\",\"7d3ba\",\"\",\"8d2ac\",\"\",\"e2995\",\"\",\"b2a93\",\"\",\"6baa7\",\"\",\"e6837\",\"\",\"dbf48\",\"\",\"0b828\",\"\",\"cc040\",\"\",\"39102\",\"\",\"1c66b\",\"\",\"a61c8\",\"\",\"d83a3\",\"\",\"6d2d3\",\"\",\"76e7e\",\"\",\"26845\",\"\",\"61f7d\",\"\",\"7a03e\",\"\",\"e4a39\",\"\",\"71328\",\"\"]],\"_defaultSort\",null,\"_columnSearchMode\",[\"^1J\",[\"5b197\",\"default\",\"7d3ba\",\"default\",\"8d2ac\",\"default\",\"e2995\",\"default\",\"b2a93\",\"default\",\"6baa7\",\"default\",\"e6837\",\"default\",\"dbf48\",\"default\",\"0b828\",\"default\",\"cc040\",\"default\",\"39102\",\"default\",\"1c66b\",\"default\",\"a61c8\",\"default\",\"d83a3\",\"default\",\"6d2d3\",\"default\",\"76e7e\",\"default\",\"26845\",\"default\",\"61f7d\",\"default\",\"7a03e\",\"default\",\"e4a39\",\"default\",\"71328\",\"default\"]],\"_columnAlternateRowBackgroundColor\",[\"^1J\",[\"5b197\",\"\",\"7d3ba\",\"\",\"8d2ac\",\"\",\"e2995\",\"\",\"b2a93\",\"\",\"6baa7\",\"\",\"e6837\",\"\",\"dbf48\",\"\",\"0b828\",\"\",\"cc040\",\"\",\"39102\",\"\",\"1c66b\",\"\",\"a61c8\",\"\",\"d83a3\",\"\",\"6d2d3\",\"\",\"76e7e\",\"\",\"26845\",\"\",\"61f7d\",\"\",\"7a03e\",\"\",\"e4a39\",\"\",\"71328\",\"\"]],\"_clearChangesetOnSave\",true,\"heightType\",\"fixed\",\"_columnTextColor\",[\"^1J\",[\"5b197\",\"\",\"7d3ba\",\"\",\"8d2ac\",\"\",\"e2995\",\"\",\"b2a93\",\"\",\"6baa7\",\"\",\"e6837\",\"\",\"dbf48\",\"\",\"0b828\",\"\",\"cc040\",\"\",\"39102\",\"\",\"1c66b\",\"\",\"a61c8\",\"\",\"d83a3\",\"\",\"6d2d3\",\"\",\"76e7e\",\"\",\"26845\",\"\",\"61f7d\",\"\",\"7a03e\",\"\",\"e4a39\",\"\",\"71328\",\"\"]],\"disableEdits\",false,\"autoColumnWidth\",false,\"_rowHeight\",\"\",\"_columnIds\",[\"^A\",[\"1c66b\",\"7a03e\",\"a61c8\",\"dbf48\",\"0b828\",\"76e7e\",\"7d3ba\",\"8d2ac\",\"cc040\",\"6d2d3\",\"d83a3\",\"e4a39\",\"5b197\",\"39102\",\"61f7d\",\"e6837\",\"71328\",\"6baa7\",\"26845\",\"b2a93\",\"e2995\"]],\"_isSaving\",false,\"_headerTextWrap\",false,\"_actionIds\",[\"^A\",[]],\"_clearChangeset\",false,\"caseSensitiveFiltering\",false,\"_limitOffsetRowCount\",null,\"selectedSourceRow\",null,\"_dynamicColumnsEnabled\",false,\"disableSave\",false,\"_columnEditableOptions\",[\"^1J\",[\"5b197\",[\"^1J\",[\"spellCheck\",false]],\"7d3ba\",[\"^1J\",[\"spellCheck\",false]],\"8d2ac\",[\"^1J\",[]],\"e2995\",[\"^1J\",[\"spellCheck\",false]],\"b2a93\",[\"^1J\",[\"spellCheck\",false]],\"6baa7\",[\"^1J\",[\"spellCheck\",false]],\"e6837\",[\"^1J\",[\"spellCheck\",false]],\"dbf48\",[\"^1J\",[]],\"0b828\",[\"^1J\",[\"showStepper\",true]],\"cc040\",[\"^1J\",[]],\"39102\",[\"^1J\",[\"spellCheck\",false]],\"1c66b\",[\"^1J\",[\"spellCheck\",false]],\"a61c8\",[\"^1J\",[\"spellCheck\",false]],\"d83a3\",[\"^1J\",[\"spellCheck\",false]],\"6d2d3\",[\"^1J\",[]],\"76e7e\",[\"^1J\",[\"spellCheck\",false]],\"26845\",[\"^1J\",[]],\"61f7d\",[\"^1J\",[]],\"7a03e\",[\"^1J\",[]],\"e4a39\",[\"^1J\",[\"spellCheck\",false]],\"71328\",[\"^1J\",[]]]],\"_toolbarPosition\",\"bottom\",\"_groupByColumns\",[\"^A\",[]],\"_toolbarButtonLabel\",[\"^1J\",[\"1a\",\"Filter\",\"3c\",\"Download\",\"4d\",\"Refresh\"]],\"_nextBeforeCursor\",\"\",\"_persistRowSelection\",false,\"_toolbarButtonIcon\",[\"^1J\",[\"1a\",\"bold/interface-text-formatting-filter-2\",\"3c\",\"bold/interface-download-button-2\",\"4d\",\"bold/interface-arrows-round-left\"]],\"changesetArray\",[],\"groupByColumns\",[],\"_toolbarButtonType\",[\"^1J\",[\"1a\",\"filter\",\"3c\",\"custom\",\"4d\",\"custom\"]],\"_columnOptionList\",[\"^1J\",[\"5b197\",[\"^1J\",[]],\"7d3ba\",[\"^1J\",[]],\"8d2ac\",[\"^1J\",[]],\"e2995\",[\"^1J\",[]],\"b2a93\",[\"^1J\",[]],\"6baa7\",[\"^1J\",[]],\"e6837\",[\"^1J\",[]],\"dbf48\",[\"^1J\",[]],\"0b828\",[\"^1J\",[]],\"cc040\",[\"^1J\",[]],\"39102\",[\"^1J\",[]],\"1c66b\",[\"^1J\",[]],\"a61c8\",[\"^1J\",[]],\"d83a3\",[\"^1J\",[]],\"6d2d3\",[\"^1J\",[]],\"76e7e\",[\"^1J\",[]],\"26845\",[\"^1J\",[]],\"61f7d\",[\"^1J\",[]],\"7a03e\",[\"^1J\",[]],\"e4a39\",[\"^1J\",[]],\"71328\",[\"^1J\",[]]]],\"_columnValueOverride\",[\"^1J\",[\"5b197\",\"\",\"7d3ba\",\"\",\"8d2ac\",\"{{ _.startCase(item) }}\",\"e2995\",\"\",\"b2a93\",\"\",\"6baa7\",\"\",\"e6837\",\"\",\"dbf48\",\"{{ _.startCase(item) }}\",\"0b828\",\"\",\"cc040\",\"\",\"39102\",\"\",\"1c66b\",\"\",\"a61c8\",\"\",\"d83a3\",\"\",\"6d2d3\",\"\",\"76e7e\",\"\",\"26845\",\"{{ _.startCase(item) }}\",\"61f7d\",\"\",\"7a03e\",\"\",\"e4a39\",\"\",\"71328\",\"{{ _.startCase(item) }}\"]],\"_showBorder\",true,\"_templatePageSize\",null,\"_dynamicColumnProperties\",[\"^1J\",[]],\"_showHeader\",true,\"_currentPage\",0,\"overflowActionsOverlayMinWidth\",null,\"_actionsOverflowPosition\",0,\"_columnKey\",[\"^1J\",[\"5b197\",\"Check Number\",\"7d3ba\",\"Account #\",\"8d2ac\",\"Institution\",\"e2995\",\"Import Tag\",\"b2a93\",\"Metadata\",\"6baa7\",\"Categorized Date\",\"e6837\",\"Category Hint\",\"dbf48\",\"Category\",\"0b828\",\"Amount\",\"cc040\",\"Month\",\"39102\",\"Full Description\",\"1c66b\",\"untitled\",\"a61c8\",\"Description\",\"d83a3\",\"Transaction ID\",\"6d2d3\",\"Week\",\"76e7e\",\"Account\",\"26845\",\"Source\",\"61f7d\",\"Date Added\",\"7a03e\",\"Date\",\"e4a39\",\"Account ID\",\"71328\",\"Categorized By\"]],\"hidden\",false,\"_toolbarButtonIds\",[\"^A\",[\"1a\",\"3c\",\"4d\"]],\"columnOrdering\",[],\"data\",\"{{ query1.data }}\",\"_cellSelection\",\"none\",\"_serverPaginated\",false,\"_linkedFilterId\",null,\"searchMode\",\"fuzzy\",\"_columnCellTooltip\",[\"^1J\",[\"5b197\",\"\",\"7d3ba\",\"\",\"8d2ac\",\"\",\"e2995\",\"\",\"b2a93\",\"\",\"6baa7\",\"\",\"e6837\",\"\",\"dbf48\",\"\",\"0b828\",\"\",\"cc040\",\"\",\"39102\",\"\",\"1c66b\",\"\",\"a61c8\",\"\",\"d83a3\",\"\",\"6d2d3\",\"\",\"76e7e\",\"\",\"26845\",\"\",\"61f7d\",\"\",\"7a03e\",\"\",\"e4a39\",\"\",\"71328\",\"\"]],\"_columnFormat\",[\"^1J\",[\"5b197\",\"string\",\"7d3ba\",\"string\",\"8d2ac\",\"tag\",\"e2995\",\"string\",\"b2a93\",\"string\",\"6baa7\",\"string\",\"e6837\",\"string\",\"dbf48\",\"tag\",\"0b828\",\"percent\",\"cc040\",\"date\",\"39102\",\"string\",\"1c66b\",\"string\",\"a61c8\",\"string\",\"d83a3\",\"string\",\"6d2d3\",\"date\",\"76e7e\",\"string\",\"26845\",\"tag\",\"61f7d\",\"date\",\"7a03e\",\"date\",\"e4a39\",\"string\",\"71328\",\"tag\"]],\"_cursorCache\",[\"^ \"],\"_calculatedPageSize\",null,\"_primaryKeyColumnId\",\"\",\"selectedDataIndex\",null,\"_columnAlignment\",[\"^1J\",[\"5b197\",\"left\",\"7d3ba\",\"left\",\"8d2ac\",\"left\",\"e2995\",\"left\",\"b2a93\",\"left\",\"6baa7\",\"left\",\"e6837\",\"left\",\"dbf48\",\"left\",\"0b828\",\"right\",\"cc040\",\"left\",\"39102\",\"left\",\"1c66b\",\"left\",\"a61c8\",\"left\",\"d83a3\",\"left\",\"6d2d3\",\"left\",\"76e7e\",\"left\",\"26845\",\"left\",\"61f7d\",\"left\",\"7a03e\",\"left\",\"e4a39\",\"left\",\"71328\",\"left\"]],\"_actionIcon\",[\"^1J\",[]],\"margin\",\"4px 8px\",\"_columnTooltip\",[\"^1J\",[\"5b197\",\"\",\"7d3ba\",\"\",\"8d2ac\",\"\",\"e2995\",\"\",\"b2a93\",\"\",\"6baa7\",\"\",\"e6837\",\"\",\"dbf48\",\"\",\"0b828\",\"\",\"cc040\",\"\",\"39102\",\"\",\"1c66b\",\"\",\"a61c8\",\"\",\"d83a3\",\"\",\"6d2d3\",\"\",\"76e7e\",\"\",\"26845\",\"\",\"61f7d\",\"\",\"7a03e\",\"\",\"e4a39\",\"\",\"71328\",\"\"]],\"_columnIcon\",[\"^1J\",[\"5b197\",\"\",\"7d3ba\",\"\",\"8d2ac\",\"\",\"e2995\",\"\",\"b2a93\",\"\",\"6baa7\",\"\",\"e6837\",\"\",\"dbf48\",\"\",\"0b828\",\"\",\"cc040\",\"\",\"39102\",\"\",\"1c66b\",\"\",\"a61c8\",\"\",\"d83a3\",\"\",\"6d2d3\",\"\",\"76e7e\",\"\",\"26845\",\"\",\"61f7d\",\"\",\"7a03e\",\"\",\"e4a39\",\"\",\"71328\",\"\"]],\"_alwaysShowRowSelectionCheckboxes\",false,\"_columnCellTooltipMode\",[\"^1J\",[\"5b197\",\"\",\"7d3ba\",\"\",\"8d2ac\",\"\",\"e2995\",\"\",\"b2a93\",\"\",\"6baa7\",\"\",\"e6837\",\"\",\"dbf48\",\"\",\"0b828\",\"\",\"cc040\",\"\",\"39102\",\"\",\"1c66b\",\"\",\"a61c8\",\"\",\"d83a3\",\"\",\"6d2d3\",\"\",\"76e7e\",\"\",\"26845\",\"\",\"61f7d\",\"\",\"7a03e\",\"\",\"e4a39\",\"\",\"71328\",\"\"]],\"_pageSize\",null,\"showInEditor\",false,\"_isAddingNewRows\",false,\"selectedSourceRows\",[],\"_enableExpandableRows\",false,\"_selectMultipleRowsOnActionClick\",\"no\",\"_columnSortDisabled\",[\"^1J\",[\"5b197\",false,\"7d3ba\",false,\"8d2ac\",false,\"e2995\",false,\"b2a93\",false,\"6baa7\",false,\"e6837\",false,\"dbf48\",false,\"0b828\",false,\"cc040\",false,\"39102\",false,\"1c66b\",false,\"a61c8\",false,\"d83a3\",false,\"6d2d3\",false,\"76e7e\",false,\"26845\",false,\"61f7d\",false,\"7a03e\",false,\"e4a39\",false,\"71328\",false]],\"_showSummaryRow\",false,\"filterStack\",null,\"_expandedRows\",null,\"changesetObject\",null,\"_actionDisabled\",[\"^1J\",[]],\"style\",[\"^1J\",[\"rowSeparator\",\"surfacePrimaryBorder\"]],\"_columnReferenceId\",[\"^1J\",[\"5b197\",\"\",\"7d3ba\",\"\",\"8d2ac\",\"\",\"e2995\",\"\",\"b2a93\",\"\",\"6baa7\",\"\",\"e6837\",\"\",\"dbf48\",\"\",\"0b828\",\"\",\"cc040\",\"\",\"39102\",\"\",\"1c66b\",\"\",\"a61c8\",\"\",\"d83a3\",\"\",\"6d2d3\",\"\",\"76e7e\",\"\",\"26845\",\"\",\"61f7d\",\"\",\"7a03e\",\"\",\"e4a39\",\"\",\"71328\",\"\"]],\"_dynamicColumnSource\",[],\"_rowSelection\",\"single\",\"_columnCaption\",[\"^1J\",[\"5b197\",\"\",\"7d3ba\",\"\",\"8d2ac\",\"\",\"e2995\",\"\",\"b2a93\",\"\",\"6baa7\",\"\",\"e6837\",\"\",\"dbf48\",\"\",\"0b828\",\"\",\"cc040\",\"\",\"39102\",\"\",\"1c66b\",\"\",\"a61c8\",\"\",\"d83a3\",\"\",\"6d2d3\",\"\",\"76e7e\",\"\",\"26845\",\"\",\"61f7d\",\"\",\"7a03e\",\"\",\"e4a39\",\"\",\"71328\",\"\"]],\"_dynamicColumnFormatOptions\",[\"^1J\",[]],\"_dynamicRowHeights\",false,\"_columnFormatOptions\",[\"^1J\",[\"5b197\",[\"^1J\",[]],\"7d3ba\",[\"^1J\",[]],\"8d2ac\",[\"^1J\",[\"automaticColors\",true]],\"e2995\",[\"^1J\",[]],\"b2a93\",[\"^1J\",[]],\"6baa7\",[\"^1J\",[]],\"e6837\",[\"^1J\",[]],\"dbf48\",[\"^1J\",[\"automaticColors\",true]],\"0b828\",[\"^1J\",[\"showSeparators\",true,\"notation\",\"standard\"]],\"cc040\",[\"^1J\",[]],\"39102\",[\"^1J\",[]],\"1c66b\",[\"^1J\",[]],\"a61c8\",[\"^1J\",[]],\"d83a3\",[\"^1J\",[]],\"6d2d3\",[\"^1J\",[]],\"76e7e\",[\"^1J\",[]],\"26845\",[\"^1J\",[\"automaticColors\",true]],\"61f7d\",[\"^1J\",[]],\"7a03e\",[\"^1J\",[]],\"e4a39\",[\"^1J\",[]],\"71328\",[\"^1J\",[\"automaticColors\",true]]]],\"_changeset\",null,\"_afterCursor\",\"\",\"_columnHeaderBackgroundColor\",[\"^1J\",[\"5b197\",\"\",\"7d3ba\",\"\",\"8d2ac\",\"\",\"e2995\",\"\",\"b2a93\",\"\",\"6baa7\",\"\",\"e6837\",\"\",\"dbf48\",\"\",\"0b828\",\"\",\"cc040\",\"\",\"39102\",\"\",\"1c66b\",\"\",\"a61c8\",\"\",\"d83a3\",\"\",\"6d2d3\",\"\",\"76e7e\",\"\",\"26845\",\"\",\"61f7d\",\"\",\"7a03e\",\"\",\"e4a39\",\"\",\"71328\",\"\"]],\"selectedRowKeys\",[],\"_columnHeaderTextColor\",[\"^1J\",[\"5b197\",\"\",\"7d3ba\",\"\",\"8d2ac\",\"\",\"e2995\",\"\",\"b2a93\",\"\",\"6baa7\",\"\",\"e6837\",\"\",\"dbf48\",\"\",\"0b828\",\"\",\"cc040\",\"\",\"39102\",\"\",\"1c66b\",\"\",\"a61c8\",\"\",\"d83a3\",\"\",\"6d2d3\",\"\",\"76e7e\",\"\",\"26845\",\"\",\"61f7d\",\"\",\"7a03e\",\"\",\"e4a39\",\"\",\"71328\",\"\"]],\"_beforeCursor\",\"\",\"_columnSummaryAggregationMode\",[\"^1J\",[\"5b197\",\"none\",\"7d3ba\",\"none\",\"8d2ac\",\"none\",\"e2995\",\"none\",\"b2a93\",\"none\",\"6baa7\",\"none\",\"e6837\",\"none\",\"dbf48\",\"none\",\"0b828\",\"none\",\"cc040\",\"none\",\"39102\",\"none\",\"1c66b\",\"none\",\"a61c8\",\"none\",\"d83a3\",\"none\",\"6d2d3\",\"none\",\"76e7e\",\"none\",\"26845\",\"none\",\"61f7d\",\"none\",\"7a03e\",\"none\",\"e4a39\",\"none\",\"71328\",\"none\"]],\"searchTerm\",\"\",\"selectedRows\",[],\"_disabledVirtualization\",false,\"_expandedRowDataIndexes\",[],\"_showColumnBorders\",false,\"_columnStatusIndicatorOptions\",[\"^1J\",[\"5b197\",[\"^1J\",[]],\"7d3ba\",[\"^1J\",[]],\"8d2ac\",[\"^1J\",[]],\"e2995\",[\"^1J\",[]],\"b2a93\",[\"^1J\",[]],\"6baa7\",[\"^1J\",[]],\"e6837\",[\"^1J\",[]],\"dbf48\",[\"^1J\",[]],\"0b828\",[\"^1J\",[]],\"cc040\",[\"^1J\",[]],\"39102\",[\"^1J\",[]],\"1c66b\",[\"^1J\",[]],\"a61c8\",[\"^1J\",[]],\"d83a3\",[\"^1J\",[]],\"6d2d3\",[\"^1J\",[]],\"76e7e\",[\"^1J\",[]],\"26845\",[\"^1J\",[]],\"61f7d\",[\"^1J\",[]],\"7a03e\",[\"^1J\",[]],\"e4a39\",[\"^1J\",[]],\"71328\",[\"^1J\",[]]]],\"overflowActionsOverlayMaxHeight\",null,\"_columnSize\",[\"^1J\",[\"5b197\",100,\"7d3ba\",100,\"8d2ac\",100,\"e2995\",100,\"b2a93\",100,\"6baa7\",100,\"e6837\",100,\"dbf48\",100,\"0b828\",100,\"cc040\",100,\"39102\",100,\"1c66b\",100,\"a61c8\",100,\"d83a3\",100,\"6d2d3\",100,\"76e7e\",100,\"26845\",100,\"61f7d\",100,\"7a03e\",100,\"e4a39\",100,\"71328\",100]],\"_serverPaginationType\",\"limitOffsetBased\",\"_columnSortMode\",[\"^1J\",[\"5b197\",\"default\",\"7d3ba\",\"default\",\"8d2ac\",\"default\",\"e2995\",\"default\",\"b2a93\",\"default\",\"6baa7\",\"default\",\"e6837\",\"default\",\"dbf48\",\"default\",\"0b828\",\"default\",\"cc040\",\"default\",\"39102\",\"default\",\"1c66b\",\"default\",\"a61c8\",\"default\",\"d83a3\",\"default\",\"6d2d3\",\"default\",\"76e7e\",\"default\",\"26845\",\"default\",\"61f7d\",\"default\",\"7a03e\",\"default\",\"e4a39\",\"default\",\"71328\",\"default\"]],\"_selectSingleRowsOnActionClick\",\"replace\",\"_showFooter\",true,\"_groupedColumnConfig\",[\"^1J\",[]],\"_dynamicColumnSize\",[\"^1J\",[]],\"_virtualizeStartIndex\",0,\"_toolbarButtonHidden\",[\"^1J\",[\"1a\",\"\",\"3c\",\"\",\"4d\",\"\"]],\"_defaultFilters\",[\"^1J\",[]],\"events\",[\"^A\",[[\"^1J\",[\"id\",\"0f90c465\",\"type\",\"widget\",\"waitMs\",\"0\",\"waitType\",\"debounce\",\"event\",\"clickToolbar\",\"method\",\"exportData\",\"pluginId\",\"dataTable\",\"targetId\",\"3c\"]],[\"^1J\",[\"id\",\"2037b2d5\",\"type\",\"widget\",\"waitMs\",\"0\",\"waitType\",\"debounce\",\"event\",\"clickToolbar\",\"method\",\"refresh\",\"pluginId\",\"dataTable\",\"targetId\",\"4d\"]]]],\"_columnEditable\",[\"^1J\",[\"5b197\",\"\",\"7d3ba\",\"\",\"8d2ac\",\"\",\"e2995\",\"\",\"b2a93\",\"\",\"6baa7\",\"\",\"e6837\",\"\",\"dbf48\",\"\",\"0b828\",\"\",\"cc040\",\"\",\"39102\",\"\",\"1c66b\",\"\",\"a61c8\",\"\",\"d83a3\",\"\",\"6d2d3\",\"\",\"76e7e\",\"\",\"26845\",\"\",\"61f7d\",\"\",\"7a03e\",\"\",\"e4a39\",\"\",\"71328\",\"\"]],\"newRows\",[],\"_rowBackgroundColor\",[],\"emptyMessage\",\"No rows found\",\"pagination\",null,\"selectedDataIndexes\",[],\"_columnEditableInNewRows\",[\"^1J\",[\"5b197\",\"\",\"7d3ba\",\"\",\"8d2ac\",\"\",\"e2995\",\"\",\"b2a93\",\"\",\"6baa7\",\"\",\"e6837\",\"\",\"dbf48\",\"\",\"0b828\",\"\",\"cc040\",\"\",\"39102\",\"\",\"1c66b\",\"\",\"a61c8\",\"\",\"d83a3\",\"\",\"6d2d3\",\"\",\"76e7e\",\"\",\"26845\",\"\",\"61f7d\",\"\",\"7a03e\",\"\",\"e4a39\",\"\",\"71328\",\"\"]],\"_columnGroupAggregationMode\",[\"^1J\",[\"5b197\",\"none\",\"7d3ba\",\"none\",\"8d2ac\",\"none\",\"e2995\",\"none\",\"b2a93\",\"none\",\"6baa7\",\"none\",\"e6837\",\"none\",\"dbf48\",\"none\",\"0b828\",\"average\",\"cc040\",\"none\",\"39102\",\"none\",\"1c66b\",\"none\",\"a61c8\",\"none\",\"d83a3\",\"none\",\"6d2d3\",\"none\",\"76e7e\",\"none\",\"26845\",\"none\",\"61f7d\",\"none\",\"7a03e\",\"none\",\"e4a39\",\"none\",\"71328\",\"none\"]],\"sortArray\",[],\"_selectedCell\",null,\"overflowType\",\"scroll\",\"selectedCell\",null,\"_defaultSelectedRow\",[\"^1J\",[\"mode\",\"none\",\"indexType\",\"display\",\"index\",0]],\"_hasNextPage\",false,\"_includeRowInChangesetArray\",false,\"_columnPosition\",[\"^1J\",[\"5b197\",\"center\",\"7d3ba\",\"center\",\"8d2ac\",\"center\",\"e2995\",\"center\",\"b2a93\",\"center\",\"6baa7\",\"center\",\"e6837\",\"center\",\"dbf48\",\"center\",\"0b828\",\"center\",\"cc040\",\"center\",\"39102\",\"center\",\"1c66b\",\"center\",\"a61c8\",\"center\",\"d83a3\",\"center\",\"6d2d3\",\"center\",\"76e7e\",\"center\",\"26845\",\"center\",\"61f7d\",\"center\",\"7a03e\",\"center\",\"e4a39\",\"center\",\"71328\",\"center\"]],\"_enableSaveActions\",true,\"_columnPlaceholder\",[\"^1J\",[\"5b197\",\"Enter value\",\"7d3ba\",\"Enter value\",\"8d2ac\",\"Select option\",\"e2995\",\"Enter value\",\"b2a93\",\"Enter value\",\"6baa7\",\"Enter value\",\"e6837\",\"Enter value\",\"dbf48\",\"Select option\",\"0b828\",\"Enter value\",\"cc040\",\"Enter value\",\"39102\",\"Enter value\",\"1c66b\",\"Enter value\",\"a61c8\",\"Enter value\",\"d83a3\",\"Enter value\",\"6d2d3\",\"Enter value\",\"76e7e\",\"Enter value\",\"26845\",\"Select option\",\"61f7d\",\"Enter value\",\"7a03e\",\"Enter value\",\"e4a39\",\"Enter value\",\"71328\",\"Select option\"]],\"_defaultFilterOperator\",\"and\",\"_actionLabel\",[\"^1J\",[]],\"_virtualizeEndIndex\",0,\"selectedRow\",null,\"_actionHidden\",[\"^1J\",[]],\"maintainSpaceWhenHidden\",false,\"_columnHidden\",[\"^1J\",[\"5b197\",\"\",\"7d3ba\",\"\",\"8d2ac\",\"\",\"e2995\",\"\",\"b2a93\",\"\",\"6baa7\",\"\",\"e6837\",\"\",\"dbf48\",\"\",\"0b828\",\"\",\"cc040\",\"\",\"39102\",\"\",\"1c66b\",\"\",\"a61c8\",\"\",\"d83a3\",\"\",\"6d2d3\",\"\",\"76e7e\",\"\",\"26845\",\"\",\"61f7d\",\"\",\"7a03e\",\"\",\"e4a39\",\"\",\"71328\",\"\"]],\"_columnLabel\",[\"^1J\",[\"5b197\",\"Check number\",\"7d3ba\",\"Account\",\"8d2ac\",\"Institution\",\"e2995\",\"Import tag\",\"b2a93\",\"Metadata\",\"6baa7\",\"Categorized date\",\"e6837\",\"Category hint\",\"dbf48\",\"Category\",\"0b828\",\"Amount\",\"cc040\",\"Month\",\"39102\",\"Full description\",\"1c66b\",\"Untitled\",\"a61c8\",\"Description\",\"d83a3\",\"Transaction id\",\"6d2d3\",\"Week\",\"76e7e\",\"Account\",\"26845\",\"Source\",\"61f7d\",\"Date added\",\"7a03e\",\"Date\",\"e4a39\",\"Account id\",\"71328\",\"Categorized by\"]],\"_showToolbar\",true]],\"^1>\",[\"^1J\",[]],\"^1?\",[\"^0\",[\"^ \",\"n\",\"position2\",\"v\",[\"^ \",\"^18\",\"grid\",\"^1C\",\"\",\"rowGroup\",\"body\",\"subcontainer\",\"\",\"row\",131.59999999999997,\"col\",0,\"height\",20.4,\"width\",12,\"tabNum\",0,\"stackPosition\",null]]],\"^1@\",null,\"^1A\",null,\"^1B\",null,\"^1C\",\"\",\"^7\",\"~m1769885208896\",\"^1D\",\"~m1769885424755\",\"^1E\",\"\",\"^1F\",null,\"^1G\",\"page1\",\"^1H\",null,\"^1I\",null]]],\"debugText\",[\"^0\",[\"^ \",\"n\",\"pluginTemplate\",\"v\",[\"^ \",\"id\",\"debugText\",\"^16\",\"c83b561a-c141-4218-98cd-e7b704618454\",\"^17\",null,\"^18\",\"widget\",\"^19\",\"TextWidget2\",\"^1:\",null,\"^1;\",null,\"^1<\",null,\"^1=\",[\"^1J\",[\"heightType\",\"auto\",\"horizontalAlign\",\"left\",\"hidden\",false,\"imageWidth\",\"fit\",\"margin\",\"4px 8px\",\"showInEditor\",false,\"verticalAlign\",\"center\",\"tooltipText\",\"\",\"value\",\"**Query Status:**\\n\\n{{ query1.isFetching ? '⏳ Loading...' : (query1.error ? '❌ Error: ' + query1.error : '✅ Success') }}\\n\\n**Data Count:** {{ query1.data ? query1.data.length : 0 }} rows\\n\\n**First Row Sample:**\\n```json\\n{{ JSON.stringify(query1.data?.[0], null, 2) }}\\n```\",\"disableMarkdown\",false,\"overflowType\",\"scroll\",\"maintainSpaceWhenHidden\",false]],\"^1>\",[\"^1J\",[]],\"^1?\",[\"^0\",[\"^ \",\"n\",\"position2\",\"v\",[\"^ \",\"^18\",\"grid\",\"^1C\",\"\",\"^1K\",\"body\",\"^1L\",\"\",\"row\",153.60000000000005,\"col\",0,\"^1M\",1.2,\"^1N\",11,\"^1O\",0,\"^1P\",null]]],\"^1@\",null,\"^1A\",null,\"^1B\",null,\"^1C\",\"\",\"^7\",\"~m1769885209450\",\"^1D\",\"~m1769885237102\",\"^1E\",\"\",\"^1F\",null,\"^1G\",\"page1\",\"^1H\",null,\"^1I\",null]]],\"lastSyncTime\",[\"^0\",[\"^ \",\"n\",\"pluginTemplate\",\"v\",[\"^ \",\"id\",\"lastSyncTime\",\"^16\",null,\"^17\",null,\"^18\",\"state\",\"^19\",\"State\",\"^1:\",null,\"^1;\",null,\"^1<\",null,\"^1=\",[\"^1J\",[\"value\",\"\"]],\"^1>\",null,\"^1?\",null,\"^1@\",null,\"^1A\",null,\"^1B\",null,\"^1C\",\"\",\"^7\",\"~m1769886488921\",\"^1D\",\"~m1769886488921\",\"^1E\",\"\",\"^1F\",null,\"^1G\",\"page1\",\"^1H\",null,\"^1I\",null]]],\"sqlExplanation\",[\"^0\",[\"^ \",\"n\",\"pluginTemplate\",\"v\",[\"^ \",\"id\",\"sqlExplanation\",\"^16\",null,\"^17\",null,\"^18\",\"state\",\"^19\",\"State\",\"^1:\",null,\"^1;\",null,\"^1<\",null,\"^1=\",[\"^1J\",[\"value\",\"\"]],\"^1>\",null,\"^1?\",null,\"^1@\",null,\"^1A\",null,\"^1B\",null,\"^1C\",\"\",\"^7\",\"~m1769886488931\",\"^1D\",\"~m1769886488931\",\"^1E\",\"\",\"^1F\",null,\"^1G\",\"page1\",\"^1H\",null,\"^1I\",null]]],\"currentSQL\",[\"^0\",[\"^ \",\"n\",\"pluginTemplate\",\"v\",[\"^ \",\"id\",\"currentSQL\",\"^16\",null,\"^17\",null,\"^18\",\"state\",\"^19\",\"State\",\"^1:\",null,\"^1;\",null,\"^1<\",null,\"^1=\",[\"^1J\",[\"value\",\"SELECT * FROM transactions LIMIT 100;\"]],\"^1>\",null,\"^1?\",null,\"^1@\",null,\"^1A\",null,\"^1B\",null,\"^1C\",\"\",\"^7\",\"~m1769886488939\",\"^1D\",\"~m1769886488939\",\"^1E\",\"\",\"^1F\",null,\"^1G\",\"page1\",\"^1H\",null,\"^1I\",null]]],\"syncStatus\",[\"^0\",[\"^ \",\"n\",\"pluginTemplate\",\"v\",[\"^ \",\"id\",\"syncStatus\",\"^16\",null,\"^17\",null,\"^18\",\"state\",\"^19\",\"State\",\"^1:\",null,\"^1;\",null,\"^1<\",null,\"^1=\",[\"^1J\",[\"value\",\"{{ 'Idle' }}\"]],\"^1>\",null,\"^1?\",null,\"^1@\",null,\"^1A\",null,\"^1B\",null,\"^1C\",\"\",\"^7\",\"~m1769886489562\",\"^1D\",\"~m1769886489562\",\"^1E\",\"\",\"^1F\",null,\"^1G\",\"page1\",\"^1H\",null,\"^1I\",null]]],\"savedViews\",[\"^0\",[\"^ \",\"n\",\"pluginTemplate\",\"v\",[\"^ \",\"id\",\"savedViews\",\"^16\",null,\"^17\",null,\"^18\",\"state\",\"^19\",\"State\",\"^1:\",null,\"^1;\",null,\"^1<\",null,\"^1=\",[\"^1J\",[\"value\",\"{{ [] }}\"]],\"^1>\",null,\"^1?\",null,\"^1@\",null,\"^1A\",null,\"^1B\",null,\"^1C\",\"\",\"^7\",\"~m1769886489575\",\"^1D\",\"~m1769886489575\",\"^1E\",\"\",\"^1F\",null,\"^1G\",\"page1\",\"^1H\",null,\"^1I\",null]]],\"truncateTransactions\",[\"^0\",[\"^ \",\"n\",\"pluginTemplate\",\"v\",[\"^ \",\"id\",\"truncateTransactions\",\"^16\",null,\"^17\",null,\"^18\",\"datasource\",\"^19\",\"RetoolTableQuery\",\"^1:\",null,\"^1;\",\"ba116730-d6f2-40e2-9689-970c350ddffd\",\"^1<\",\"retool_db\",\"^1=\",[\"^1J\",[\"queryRefreshTime\",\"\",\"allowedGroupIds\",[\"^A\",[]],\"streamResponse\",false,\"records\",\"\",\"lastReceivedFromResourceAt\",null,\"isFunction\",false,\"databasePasswordOverride\",\"\",\"functionParameters\",null,\"queryDisabledMessage\",\"\",\"servedFromCache\",false,\"offlineUserQueryInputs\",\"\",\"functionDescription\",null,\"successMessage\",\"\",\"queryDisabled\",\"\",\"playgroundQuerySaveId\",\"latest\",\"workflowParams\",null,\"resourceNameOverride\",\"\",\"runWhenModelUpdates\",false,\"workflowRunExecutionType\",\"sync\",\"showFailureToaster\",true,\"query\",\"\",\"playgroundQueryUuid\",\"\",\"playgroundQueryId\",null,\"error\",null,\"workflowRunBodyType\",\"raw\",\"privateParams\",[\"^A\",[]],\"queryRunOnSelectorUpdate\",false,\"runWhenPageLoadsDelay\",\"\",\"data\",null,\"recordId\",\"\",\"importedQueryInputs\",[\"^1J\",[]],\"isImported\",false,\"showSuccessToaster\",false,\"cacheKeyTtl\",\"\",\"filterBy\",\"[]\",\"requestSentTimestamp\",null,\"databaseHostOverride\",\"\",\"metadata\",null,\"queryRunTime\",null,\"actionType\",\"DELETE_BY\",\"changesetObject\",\"\",\"offlineOptimisticResponse\",null,\"errorTransformer\",\"return data.error\",\"finished\",null,\"databaseNameOverride\",\"\",\"confirmationMessage\",null,\"isFetching\",false,\"changeset\",\"\",\"rawData\",null,\"queryTriggerDelay\",\"0\",\"resourceTypeOverride\",null,\"watchedParams\",[\"^A\",[]],\"enableErrorTransformer\",false,\"databaseWarehouseOverride\",\"\",\"enableBulkUpdates\",true,\"showLatestVersionUpdatedWarning\",false,\"timestamp\",0,\"importedQueryDefaults\",[\"^1J\",[]],\"enableTransformer\",false,\"showUpdateSetValueDynamicallyToggle\",true,\"overrideOrgCacheForUserCache\",false,\"bulkUpdatePrimaryKey\",\"\",\"runWhenPageLoads\",false,\"transformer\",\"return data\",\"events\",[\"^A\",[]],\"tableName\",\"transactions\",\"queryTimeout\",\"10000\",\"workflowId\",null,\"requireConfirmation\",false,\"queryFailureConditions\",\"\",\"changesetIsObject\",false,\"enableCaching\",false,\"allowedGroups\",[\"^A\",[]],\"databaseUsernameOverride\",\"\",\"databaseRoleOverride\",\"\",\"doNotThrowOnNoOp\",true,\"offlineQueryType\",\"None\",\"queryThrottleTime\",\"750\",\"updateSetValueDynamically\",false,\"notificationDuration\",4.5]],\"^1>\",null,\"^1?\",null,\"^1@\",null,\"^1A\",null,\"^1B\",null,\"^1C\",\"\",\"^7\",\"~m1769886669375\",\"^1D\",\"~m1769886674860\",\"^1E\",\"\",\"^1F\",null,\"^1G\",\"page1\",\"^1H\",null,\"^1I\",null]]],\"queryResults\",[\"^0\",[\"^ \",\"n\",\"pluginTemplate\",\"v\",[\"^ \",\"id\",\"queryResults\",\"^16\",null,\"^17\",null,\"^18\",\"datasource\",\"^19\",\"SqlQueryUnified\",\"^1:\",null,\"^1;\",\"ba116730-d6f2-40e2-9689-970c350ddffd\",\"^1<\",\"retool_db\",\"^1=\",[\"^1J\",[\"queryRefreshTime\",\"\",\"allowedGroupIds\",[\"^A\",[]],\"streamResponse\",false,\"records\",\"\",\"lastReceivedFromResourceAt\",null,\"isFunction\",false,\"databasePasswordOverride\",\"\",\"functionParameters\",null,\"queryDisabledMessage\",\"\",\"servedFromCache\",false,\"offlineUserQueryInputs\",\"\",\"functionDescription\",null,\"successMessage\",\"\",\"queryDisabled\",\"\",\"playgroundQuerySaveId\",\"latest\",\"workflowParams\",null,\"resourceNameOverride\",\"\",\"runWhenModelUpdates\",false,\"workflowRunExecutionType\",\"sync\",\"showFailureToaster\",true,\"query\",\"-- Execute dynamic SQL stored in currentSQL variable against transactions table.\\n{{ currentSQL.value }}\",\"playgroundQueryUuid\",\"\",\"playgroundQueryId\",null,\"error\",null,\"workflowRunBodyType\",\"raw\",\"privateParams\",[\"^A\",[]],\"queryRunOnSelectorUpdate\",false,\"runWhenPageLoadsDelay\",\"\",\"data\",null,\"recordId\",\"\",\"importedQueryInputs\",[\"^1J\",[]],\"_additionalScope\",[\"^A\",[]],\"isImported\",false,\"showSuccessToaster\",false,\"dataArray\",[\"^A\",[]],\"cacheKeyTtl\",\"\",\"filterBy\",\"\",\"requestSentTimestamp\",null,\"databaseHostOverride\",\"\",\"metadata\",null,\"editorMode\",\"sql\",\"queryRunTime\",null,\"actionType\",\"\",\"changesetObject\",\"\",\"shouldUseLegacySql\",false,\"offlineOptimisticResponse\",null,\"errorTransformer\",\"return data.error\",\"finished\",null,\"databaseNameOverride\",\"\",\"confirmationMessage\",null,\"isFetching\",false,\"changeset\",\"\",\"rawData\",null,\"queryTriggerDelay\",\"0\",\"resourceTypeOverride\",null,\"watchedParams\",[\"^A\",[]],\"enableErrorTransformer\",false,\"databaseWarehouseOverride\",\"\",\"enableBulkUpdates\",false,\"showLatestVersionUpdatedWarning\",false,\"timestamp\",0,\"importedQueryDefaults\",[\"^1J\",[]],\"enableTransformer\",false,\"showUpdateSetValueDynamicallyToggle\",true,\"overrideOrgCacheForUserCache\",false,\"bulkUpdatePrimaryKey\",\"\",\"runWhenPageLoads\",false,\"transformer\",\"return data\",\"events\",[\"^A\",[]],\"tableName\",\"\",\"queryTimeout\",\"10000\",\"workflowId\",null,\"requireConfirmation\",false,\"queryFailureConditions\",\"\",\"changesetIsObject\",false,\"enableCaching\",false,\"allowedGroups\",[\"^A\",[]],\"databaseUsernameOverride\",\"\",\"databaseRoleOverride\",\"\",\"shouldEnableBatchQuerying\",false,\"doNotThrowOnNoOp\",false,\"offlineQueryType\",\"None\",\"queryThrottleTime\",\"750\",\"updateSetValueDynamically\",false,\"notificationDuration\",4.5]],\"^1>\",null,\"^1?\",null,\"^1@\",null,\"^1A\",null,\"^1B\",null,\"^1C\",\"\",\"^7\",\"~m1769887422854\",\"^1D\",\"~m1769887423169\",\"^1E\",\"\",\"^1F\",null,\"^1G\",\"page1\",\"^1H\",null,\"^1I\",null]]],\"syncToRetoolDB\",[\"^0\",[\"^ \",\"n\",\"pluginTemplate\",\"v\",[\"^ \",\"id\",\"syncToRetoolDB\",\"^16\",null,\"^17\",null,\"^18\",\"datasource\",\"^19\",\"JavascriptQuery\",\"^1:\",null,\"^1;\",\"JavascriptQuery\",\"^1<\",null,\"^1=\",[\"^1J\",[\"queryRefreshTime\",\"\",\"allowedGroupIds\",[\"^A\",[]],\"streamResponse\",false,\"lastReceivedFromResourceAt\",null,\"isFunction\",false,\"functionParameters\",null,\"queryDisabledMessage\",\"\",\"servedFromCache\",false,\"offlineUserQueryInputs\",\"\",\"functionDescription\",null,\"successMessage\",\"\",\"queryDisabled\",\"\",\"playgroundQuerySaveId\",\"latest\",\"workflowParams\",null,\"resourceNameOverride\",\"\",\"runWhenModelUpdates\",false,\"workflowRunExecutionType\",\"sync\",\"showFailureToaster\",true,\"query\",\"// Placeholder sync function: currently only updates status and timestamp.\\n// Full row-level sync requires an insert query which is not yet available.\\n\\nconst rows = query1.data || [];\\n\\nif (!rows.length) {\\n  syncStatus.setValue('No rows returned from Google Sheets; nothing to sync.');\\n  return { inserted: 0 };\\n}\\n\\nconst now = new Date().toISOString();\\nlastSyncTime.setValue(now);\\nsyncStatus.setValue(`Sync simulated at ${now}, ${rows.length} rows (insert logic pending).`);\\n\\nreturn { inserted: rows.length, syncedAt: now };\",\"playgroundQueryUuid\",\"\",\"playgroundQueryId\",null,\"error\",null,\"workflowRunBodyType\",\"raw\",\"privateParams\",[\"^A\",[]],\"queryRunOnSelectorUpdate\",false,\"runWhenPageLoadsDelay\",\"\",\"data\",null,\"importedQueryInputs\",[\"^1J\",[]],\"_additionalScope\",[\"^A\",[]],\"isImported\",false,\"showSuccessToaster\",false,\"cacheKeyTtl\",\"\",\"requestSentTimestamp\",null,\"metadata\",null,\"queryRunTime\",null,\"changesetObject\",\"\",\"offlineOptimisticResponse\",null,\"errorTransformer\",\"return data.error\",\"finished\",null,\"confirmationMessage\",null,\"isFetching\",false,\"changeset\",\"\",\"rawData\",null,\"queryTriggerDelay\",\"0\",\"resourceTypeOverride\",null,\"watchedParams\",[\"^A\",[]],\"enableErrorTransformer\",false,\"showLatestVersionUpdatedWarning\",false,\"timestamp\",0,\"importedQueryDefaults\",[\"^1J\",[]],\"enableTransformer\",false,\"showUpdateSetValueDynamicallyToggle\",true,\"overrideOrgCacheForUserCache\",false,\"runWhenPageLoads\",false,\"transformer\",\"return data\",\"events\",[\"^A\",[]],\"queryTimeout\",\"10000\",\"workflowId\",null,\"requireConfirmation\",false,\"queryFailureConditions\",\"\",\"changesetIsObject\",false,\"enableCaching\",false,\"allowedGroups\",[\"^A\",[]],\"offlineQueryType\",\"None\",\"queryThrottleTime\",\"750\",\"updateSetValueDynamically\",false,\"notificationDuration\",4.5]],\"^1>\",null,\"^1?\",null,\"^1@\",null,\"^1A\",null,\"^1B\",null,\"^1C\",\"\",\"^7\",\"~m1769887428694\",\"^1D\",\"~m1769887428884\",\"^1E\",\"\",\"^1F\",null,\"^1G\",\"page1\",\"^1H\",null,\"^1I\",null]]],\"loadViewQuery\",[\"^0\",[\"^ \",\"n\",\"pluginTemplate\",\"v\",[\"^ \",\"id\",\"loadViewQuery\",\"^16\",null,\"^17\",null,\"^18\",\"datasource\",\"^19\",\"JavascriptQuery\",\"^1:\",null,\"^1;\",\"JavascriptQuery\",\"^1<\",null,\"^1=\",[\"^1J\",[\"queryRefreshTime\",\"\",\"allowedGroupIds\",[\"^A\",[]],\"streamResponse\",false,\"lastReceivedFromResourceAt\",null,\"isFunction\",false,\"functionParameters\",null,\"queryDisabledMessage\",\"\",\"servedFromCache\",false,\"offlineUserQueryInputs\",\"\",\"functionDescription\",null,\"successMessage\",\"\",\"queryDisabled\",\"\",\"playgroundQuerySaveId\",\"latest\",\"workflowParams\",null,\"resourceNameOverride\",\"\",\"runWhenModelUpdates\",false,\"workflowRunExecutionType\",\"sync\",\"showFailureToaster\",true,\"query\",\"// Documentation:\\n//   Loads a saved view into the interface. This implementation attempts to load\\n//   from the selected row in dataTable if available, otherwise throws an error.\\n//   The selected view's SQL and description are loaded into the currentSQL and\\n//   sqlExplanation states respectively.\\n// Returns:\\n//   {\\n//     name: string // The name of the loaded view\\n//     sql: string // The SQL query from the view  \\n//     description: string // The description of the view\\n//   }\\n\\nconst views = Array.isArray(savedViews.value) ? savedViews.value : [];\\n\\n// Try to get view name from selected table row\\nconst selectedView = dataTable?.selectedRow;\\n\\nif (!selectedView || !selectedView.name) {\\n  throw new Error('No view selected. Please select a view from the table.');\\n}\\n\\nconst name = selectedView.name;\\nconst view = views.find((v) => v?.name === name);\\n\\nif (!view) {\\n  throw new Error(`View not found: ${name}`);\\n}\\n\\ncurrentSQL.setValue(view.sql);\\nsqlExplanation.setValue(view.description || '');\\n\\nreturn view;\",\"playgroundQueryUuid\",\"\",\"playgroundQueryId\",null,\"error\",null,\"workflowRunBodyType\",\"raw\",\"privateParams\",[\"^A\",[]],\"queryRunOnSelectorUpdate\",false,\"runWhenPageLoadsDelay\",\"\",\"data\",null,\"importedQueryInputs\",[\"^1J\",[]],\"_additionalScope\",[\"^A\",[]],\"isImported\",false,\"showSuccessToaster\",false,\"cacheKeyTtl\",\"\",\"requestSentTimestamp\",null,\"metadata\",null,\"queryRunTime\",null,\"changesetObject\",\"\",\"offlineOptimisticResponse\",null,\"errorTransformer\",\"return data.error\",\"finished\",null,\"confirmationMessage\",null,\"isFetching\",false,\"changeset\",\"\",\"rawData\",null,\"queryTriggerDelay\",\"0\",\"resourceTypeOverride\",null,\"watchedParams\",[\"^A\",[]],\"enableErrorTransformer\",false,\"showLatestVersionUpdatedWarning\",false,\"timestamp\",0,\"importedQueryDefaults\",[\"^1J\",[]],\"enableTransformer\",false,\"showUpdateSetValueDynamicallyToggle\",true,\"overrideOrgCacheForUserCache\",false,\"runWhenPageLoads\",false,\"transformer\",\"return data\",\"events\",[\"^A\",[]],\"queryTimeout\",\"10000\",\"workflowId\",null,\"requireConfirmation\",false,\"queryFailureConditions\",\"\",\"changesetIsObject\",false,\"enableCaching\",false,\"allowedGroups\",[\"^A\",[]],\"offlineQueryType\",\"None\",\"queryThrottleTime\",\"750\",\"updateSetValueDynamically\",false,\"notificationDuration\",4.5]],\"^1>\",null,\"^1?\",null,\"^1@\",null,\"^1A\",null,\"^1B\",null,\"^1C\",\"\",\"^7\",\"~m1769887503233\",\"^1D\",\"~m1769887503441\",\"^1E\",\"\",\"^1F\",null,\"^1G\",\"page1\",\"^1H\",null,\"^1I\",null]]],\"appTitle\",[\"^0\",[\"^ \",\"n\",\"pluginTemplate\",\"v\",[\"^ \",\"id\",\"appTitle\",\"^16\",\"3b22abef-fc85-4491-842b-795d475b8c9e\",\"^17\",null,\"^18\",\"widget\",\"^19\",\"TextWidget2\",\"^1:\",null,\"^1;\",null,\"^1<\",null,\"^1=\",[\"^1J\",[\"heightType\",\"auto\",\"horizontalAlign\",\"left\",\"hidden\",false,\"imageWidth\",\"fit\",\"margin\",\"4px 8px\",\"showInEditor\",false,\"verticalAlign\",\"center\",\"tooltipText\",\"\",\"value\",\"# Transaction Query Builder\",\"disableMarkdown\",false,\"overflowType\",\"scroll\",\"maintainSpaceWhenHidden\",false]],\"^1>\",[\"^1J\",[]],\"^1?\",[\"^0\",[\"^ \",\"n\",\"position2\",\"v\",[\"^ \",\"^18\",\"grid\",\"^1C\",\"\",\"^1K\",\"body\",\"^1L\",\"\",\"row\",0.4,\"col\",0,\"^1M\",1.2,\"^1N\",12,\"^1O\",0,\"^1P\",null]]],\"^1@\",null,\"^1A\",null,\"^1B\",null,\"^1C\",\"\",\"^7\",\"~m1769887546783\",\"^1D\",\"~m1769887547807\",\"^1E\",\"\",\"^1F\",null,\"^1G\",\"page1\",\"^1H\",null,\"^1I\",null]]],\"syncNowButton\",[\"^0\",[\"^ \",\"n\",\"pluginTemplate\",\"v\",[\"^ \",\"id\",\"syncNowButton\",\"^16\",\"9e9898d6-321e-43e8-bc2b-fb818bdccce2\",\"^17\",null,\"^18\",\"widget\",\"^19\",\"ButtonWidget2\",\"^1:\",null,\"^1;\",null,\"^1<\",null,\"^1=\",[\"^1J\",[\"heightType\",\"fixed\",\"horizontalAlign\",\"stretch\",\"clickable\",false,\"iconAfter\",\"\",\"submitTargetId\",null,\"hidden\",false,\"ariaLabel\",\"\",\"text\",\"Sync Now\",\"margin\",\"4px 8px\",\"showInEditor\",false,\"tooltipText\",\"\",\"allowWrap\",true,\"styleVariant\",\"solid\",\"submit\",false,\"iconBefore\",\"\",\"events\",[\"^A\",[[\"^1J\",[\"method\",\"run\",\"params\",[\"^1J\",[\"src\",\"syncStatus.setValue('Syncing from Google Sheets...');\\nquery1.trigger();\"]],\"targetId\",null,\"pluginId\",\"\",\"waitType\",\"debounce\",\"event\",\"click\",\"type\",\"script\",\"id\",\"8f5b6b01\",\"waitMs\",\"0\"]]]],\"loading\",false,\"loaderPosition\",\"auto\",\"disabled\",false,\"maintainSpaceWhenHidden\",false]],\"^1>\",[\"^1J\",[]],\"^1?\",[\"^0\",[\"^ \",\"n\",\"position2\",\"v\",[\"^ \",\"^18\",\"grid\",\"^1C\",\"syncControlsContainer\",\"^1K\",\"body\",\"^1L\",\"00030\",\"row\",0,\"col\",0,\"^1M\",1,\"^1N\",2,\"^1O\",0,\"^1P\",[\"^ \",\"ordinal\",0,\"widthType\",\"fixed\",\"^1N\",0,\"^1M\",0]]]],\"^1@\",null,\"^1A\",null,\"^1B\",null,\"^1C\",\"\",\"^7\",\"~m1769887547709\",\"^1D\",\"~m1769887620285\",\"^1E\",\"\",\"^1F\",null,\"^1G\",\"page1\",\"^1H\",null,\"^1I\",null]]],\"syncControlsContainer\",[\"^0\",[\"^ \",\"n\",\"pluginTemplate\",\"v\",[\"^ \",\"id\",\"syncControlsContainer\",\"^16\",\"ec4ec0ec-9af1-4a84-958b-dd3b401b5089\",\"^17\",null,\"^18\",\"widget\",\"^19\",\"ContainerWidget2\",\"^1:\",null,\"^1;\",null,\"^1<\",null,\"^1=\",[\"^1J\",[\"_direction\",\"horizontal\",\"_disabledByIndex\",[\"^A\",[\"\"]],\"heightType\",\"auto\",\"currentViewKey\",null,\"iconByIndex\",[],\"_flexWrap\",false,\"clickable\",false,\"_iconByIndex\",[\"^A\",[\"\"]],\"headerPadding\",\"4px 12px\",\"showFooterBorder\",true,\"_align\",\"start\",\"enableFullBleed\",false,\"showBorder\",true,\"hidden\",false,\"showHeader\",false,\"hoistFetching\",false,\"margin\",\"4px 8px\",\"views\",[],\"showInEditor\",false,\"tooltipText\",\"\",\"padding\",\"12px\",\"_justify\",\"start\",\"style\",[\"^1J\",[\"border\",\"surfacePrimaryBorder\",\"borderRadius\",\"8px\"]],\"hiddenByIndex\",[],\"_hiddenByIndex\",[\"^A\",[\"\"]],\"currentViewIndex\",null,\"_hasMigratedNestedItems\",true,\"transition\",\"none\",\"showHeaderBorder\",true,\"footerPadding\",\"4px 12px\",\"itemMode\",\"static\",\"_gap\",\"\",\"_tooltipByIndex\",[\"^A\",[\"\"]],\"tooltipByIndex\",[],\"showFooter\",false,\"_viewKeys\",[\"^A\",[\"View 1\"]],\"_type\",\"grid\",\"events\",[\"^15\",[]],\"_ids\",[\"^A\",[\"00030\"]],\"viewKeys\",[],\"iconPositionByIndex\",[],\"_iconPositionByIndex\",[\"^A\",[\"\"]],\"hovered\",false,\"loading\",false,\"overflowType\",\"scroll\",\"disabled\",false,\"_labels\",[\"^A\",[\"\"]],\"disabledByIndex\",[],\"maintainSpaceWhenHidden\",false,\"showBody\",true,\"labels\",[]]],\"^1>\",[\"^1J\",[]],\"^1?\",[\"^0\",[\"^ \",\"n\",\"position2\",\"v\",[\"^ \",\"^18\",\"grid\",\"^1C\",\"\",\"^1K\",\"body\",\"^1L\",\"\",\"row\",2.3999999999999972,\"col\",0,\"^1M\",1.9999999999999996,\"^1N\",12,\"^1O\",0,\"^1P\",[\"^ \",\"^1Q\",0,\"^1R\",\"fixed\",\"^1N\",0,\"^1M\",0]]]],\"^1@\",null,\"^1A\",null,\"^1B\",null,\"^1C\",\"\",\"^7\",\"~m1769887547730\",\"^1D\",\"~m1769887547730\",\"^1E\",\"\",\"^1F\",null,\"^1G\",\"page1\",\"^1H\",null,\"^1I\",null]]],\"lastSyncTimeText\",[\"^0\",[\"^ \",\"n\",\"pluginTemplate\",\"v\",[\"^ \",\"id\",\"lastSyncTimeText\",\"^16\",\"5763469c-30cb-4ad0-b959-3c3b005a0fbf\",\"^17\",null,\"^18\",\"widget\",\"^19\",\"TextWidget2\",\"^1:\",null,\"^1;\",null,\"^1<\",null,\"^1=\",[\"^1J\",[\"heightType\",\"auto\",\"horizontalAlign\",\"left\",\"hidden\",false,\"imageWidth\",\"fit\",\"margin\",\"4px 8px\",\"showInEditor\",false,\"verticalAlign\",\"center\",\"tooltipText\",\"\",\"value\",\"**Last synced:** {{ lastSyncTime.value || 'Never' }}\",\"disableMarkdown\",false,\"overflowType\",\"scroll\",\"maintainSpaceWhenHidden\",false]],\"^1>\",[\"^1J\",[]],\"^1?\",[\"^0\",[\"^ \",\"n\",\"position2\",\"v\",[\"^ \",\"^18\",\"grid\",\"^1C\",\"syncControlsContainer\",\"^1K\",\"body\",\"^1L\",\"00030\",\"row\",0,\"col\",3,\"^1M\",4.199999999999999,\"^1N\",4,\"^1O\",0,\"^1P\",[\"^ \",\"^1Q\",1,\"^1R\",\"fixed\",\"^1N\",0,\"^1M\",0]]]],\"^1@\",null,\"^1A\",null,\"^1B\",null,\"^1C\",\"\",\"^7\",\"~m1769887549875\",\"^1D\",\"~m1769887607882\",\"^1E\",\"\",\"^1F\",null,\"^1G\",\"page1\",\"^1H\",null,\"^1I\",null]]],\"syncStatusText\",[\"^0\",[\"^ \",\"n\",\"pluginTemplate\",\"v\",[\"^ \",\"id\",\"syncStatusText\",\"^16\",\"01e70e69-d153-41ed-af65-d7a0a20a2dd5\",\"^17\",null,\"^18\",\"widget\",\"^19\",\"TextWidget2\",\"^1:\",null,\"^1;\",null,\"^1<\",null,\"^1=\",[\"^1J\",[\"heightType\",\"auto\",\"horizontalAlign\",\"left\",\"hidden\",false,\"imageWidth\",\"fit\",\"margin\",\"4px 8px\",\"showInEditor\",false,\"verticalAlign\",\"center\",\"tooltipText\",\"\",\"value\",\"{{ syncStatus.value || 'Idle' }}\",\"disableMarkdown\",false,\"overflowType\",\"scroll\",\"maintainSpaceWhenHidden\",false]],\"^1>\",[\"^1J\",[]],\"^1?\",[\"^0\",[\"^ \",\"n\",\"position2\",\"v\",[\"^ \",\"^18\",\"grid\",\"^1C\",\"syncControlsContainer\",\"^1K\",\"body\",\"^1L\",\"00030\",\"row\",0,\"col\",8,\"^1M\",4.199999999999999,\"^1N\",4,\"^1O\",0,\"^1P\",[\"^ \",\"^1Q\",2,\"^1R\",\"fixed\",\"^1N\",0,\"^1M\",0]]]],\"^1@\",null,\"^1A\",null,\"^1B\",null,\"^1C\",\"\",\"^7\",\"~m1769887549891\",\"^1D\",\"~m1769887607717\",\"^1E\",\"\",\"^1F\",null,\"^1G\",\"page1\",\"^1H\",null,\"^1I\",null]]],\"leftSidebarContainer\",[\"^0\",[\"^ \",\"n\",\"pluginTemplate\",\"v\",[\"^ \",\"id\",\"leftSidebarContainer\",\"^16\",\"d2fb7889-dc1d-444c-9b6b-78a83e21ff63\",\"^17\",null,\"^18\",\"widget\",\"^19\",\"ContainerWidget2\",\"^1:\",null,\"^1;\",null,\"^1<\",null,\"^1=\",[\"^1J\",[\"_direction\",\"horizontal\",\"_disabledByIndex\",[\"^A\",[\"\"]],\"heightType\",\"auto\",\"currentViewKey\",null,\"iconByIndex\",[],\"_flexWrap\",false,\"clickable\",false,\"_iconByIndex\",[\"^A\",[\"\"]],\"headerPadding\",\"4px 12px\",\"showFooterBorder\",true,\"_align\",\"start\",\"enableFullBleed\",false,\"showBorder\",true,\"hidden\",false,\"showHeader\",true,\"hoistFetching\",false,\"margin\",\"4px 8px\",\"views\",[],\"showInEditor\",false,\"tooltipText\",\"\",\"padding\",\"12px\",\"_justify\",\"start\",\"style\",[\"^1J\",[\"border\",\"surfacePrimaryBorder\",\"borderRadius\",\"8px\"]],\"hiddenByIndex\",[],\"_hiddenByIndex\",[\"^A\",[\"\"]],\"currentViewIndex\",null,\"_hasMigratedNestedItems\",true,\"transition\",\"none\",\"showHeaderBorder\",true,\"footerPadding\",\"4px 12px\",\"itemMode\",\"static\",\"_gap\",\"\",\"_tooltipByIndex\",[\"^A\",[\"\"]],\"tooltipByIndex\",[],\"showFooter\",false,\"_viewKeys\",[\"^A\",[\"View 1\"]],\"_type\",\"grid\",\"events\",[\"^15\",[]],\"_ids\",[\"^A\",[\"00030\"]],\"viewKeys\",[],\"iconPositionByIndex\",[],\"_iconPositionByIndex\",[\"^A\",[\"\"]],\"hovered\",false,\"loading\",false,\"overflowType\",\"scroll\",\"disabled\",false,\"_labels\",[\"^A\",[\"\"]],\"disabledByIndex\",[],\"maintainSpaceWhenHidden\",false,\"showBody\",true,\"labels\",[]]],\"^1>\",[\"^1J\",[]],\"^1?\",[\"^0\",[\"^ \",\"n\",\"position2\",\"v\",[\"^ \",\"^18\",\"grid\",\"^1C\",\"\",\"^1K\",\"body\",\"^1L\",\"\",\"row\",4.800000000000002,\"col\",0,\"^1M\",102,\"^1N\",3,\"^1O\",0,\"^1P\",[\"^ \",\"^1Q\",0,\"^1R\",\"fixed\",\"^1N\",0,\"^1M\",0]]]],\"^1@\",null,\"^1A\",null,\"^1B\",null,\"^1C\",\"\",\"^7\",\"~m1769887549904\",\"^1D\",\"~m1769887572921\",\"^1E\",\"\",\"^1F\",null,\"^1G\",\"page1\",\"^1H\",null,\"^1I\",null]]],\"saveViewButton\",[\"^0\",[\"^ \",\"n\",\"pluginTemplate\",\"v\",[\"^ \",\"id\",\"saveViewButton\",\"^16\",\"12a05da8-996c-4ef9-9770-fd03ac505c0a\",\"^17\",null,\"^18\",\"widget\",\"^19\",\"ButtonWidget2\",\"^1:\",null,\"^1;\",null,\"^1<\",null,\"^1=\",[\"^1J\",[\"heightType\",\"fixed\",\"horizontalAlign\",\"stretch\",\"clickable\",false,\"iconAfter\",\"\",\"submitTargetId\",null,\"hidden\",false,\"ariaLabel\",\"\",\"text\",\"Save Current View\",\"margin\",\"4px 8px\",\"showInEditor\",false,\"tooltipText\",\"\",\"allowWrap\",true,\"styleVariant\",\"outline\",\"submit\",false,\"iconBefore\",\"\",\"events\",[\"^15\",[]],\"loading\",false,\"loaderPosition\",\"auto\",\"disabled\",false,\"maintainSpaceWhenHidden\",false]],\"^1>\",[\"^1J\",[]],\"^1?\",[\"^0\",[\"^ \",\"n\",\"position2\",\"v\",[\"^ \",\"^18\",\"grid\",\"^1C\",\"leftSidebarContainer\",\"^1K\",\"body\",\"^1L\",\"00030\",\"row\",0,\"col\",0,\"^1M\",1,\"^1N\",12,\"^1O\",0,\"^1P\",[\"^ \",\"^1Q\",1,\"^1R\",\"fixed\",\"^1N\",0,\"^1M\",0]]]],\"^1@\",null,\"^1A\",null,\"^1B\",null,\"^1C\",\"\",\"^7\",\"~m1769887550229\",\"^1D\",\"~m1769887550989\",\"^1E\",\"\",\"^1F\",null,\"^1G\",\"page1\",\"^1H\",null,\"^1I\",null]]],\"savedViewsTitle\",[\"^0\",[\"^ \",\"n\",\"pluginTemplate\",\"v\",[\"^ \",\"id\",\"savedViewsTitle\",\"^16\",\"e0c94d2a-7df6-4a50-9c1c-e36bc9f72de9\",\"^17\",null,\"^18\",\"widget\",\"^19\",\"TextWidget2\",\"^1:\",null,\"^1;\",null,\"^1<\",null,\"^1=\",[\"^1J\",[\"heightType\",\"auto\",\"horizontalAlign\",\"left\",\"hidden\",false,\"imageWidth\",\"fit\",\"margin\",\"4px 8px\",\"showInEditor\",false,\"verticalAlign\",\"center\",\"tooltipText\",\"\",\"value\",\"### Saved Views\",\"disableMarkdown\",false,\"overflowType\",\"scroll\",\"maintainSpaceWhenHidden\",false]],\"^1>\",[\"^1J\",[]],\"^1?\",[\"^0\",[\"^ \",\"n\",\"position2\",\"v\",[\"^ \",\"^18\",\"grid\",\"^1C\",\"leftSidebarContainer\",\"^1K\",\"header\",\"^1L\",\"00030\",\"row\",0,\"col\",0,\"^1M\",2.8000000000000003,\"^1N\",12,\"^1O\",0,\"^1P\",null]]],\"^1@\",null,\"^1A\",null,\"^1B\",null,\"^1C\",\"\",\"^7\",\"~m1769887550299\",\"^1D\",\"~m1769887551658\",\"^1E\",\"\",\"^1F\",null,\"^1G\",\"page1\",\"^1H\",null,\"^1I\",null]]],\"savedViewsList\",[\"^0\",[\"^ \",\"n\",\"pluginTemplate\",\"v\",[\"^ \",\"id\",\"savedViewsList\",\"^16\",\"a57bb283-191e-41cd-97eb-40baa313a351\",\"^17\",null,\"^18\",\"widget\",\"^19\",\"TextWidget2\",\"^1:\",null,\"^1;\",null,\"^1<\",null,\"^1=\",[\"^1J\",[\"heightType\",\"auto\",\"horizontalAlign\",\"left\",\"hidden\",false,\"imageWidth\",\"fit\",\"margin\",\"4px 8px\",\"showInEditor\",false,\"verticalAlign\",\"center\",\"tooltipText\",\"\",\"value\",\"{{ (savedViews.value && savedViews.value.length > 0) ? savedViews.value.map(v => `• ${v.name}`).join('\\\\n') : '_No saved views yet_' }}\",\"disableMarkdown\",false,\"overflowType\",\"scroll\",\"maintainSpaceWhenHidden\",false]],\"^1>\",[\"^1J\",[]],\"^1?\",[\"^0\",[\"^ \",\"n\",\"position2\",\"v\",[\"^ \",\"^18\",\"grid\",\"^1C\",\"leftSidebarContainer\",\"^1K\",\"body\",\"^1L\",\"00030\",\"row\",1.6,\"col\",0,\"^1M\",27.600000000000005,\"^1N\",12,\"^1O\",0,\"^1P\",[\"^ \",\"^1Q\",0,\"^1R\",\"fixed\",\"^1N\",0,\"^1M\",0]]]],\"^1@\",null,\"^1A\",null,\"^1B\",null,\"^1C\",\"\",\"^7\",\"~m1769887553621\",\"^1D\",\"~m1769887607741\",\"^1E\",\"\",\"^1F\",null,\"^1G\",\"page1\",\"^1H\",null,\"^1I\",null]]],\"centerQueryContainer\",[\"^0\",[\"^ \",\"n\",\"pluginTemplate\",\"v\",[\"^ \",\"id\",\"centerQueryContainer\",\"^16\",\"29f53eaa-e430-4b57-8bc6-76d53606cddd\",\"^17\",null,\"^18\",\"widget\",\"^19\",\"ContainerWidget2\",\"^1:\",null,\"^1;\",null,\"^1<\",null,\"^1=\",[\"^1J\",[\"_direction\",\"horizontal\",\"_disabledByIndex\",[\"^A\",[\"\"]],\"heightType\",\"auto\",\"currentViewKey\",null,\"iconByIndex\",[],\"_flexWrap\",false,\"clickable\",false,\"_iconByIndex\",[\"^A\",[\"\"]],\"headerPadding\",\"4px 12px\",\"showFooterBorder\",true,\"_align\",\"start\",\"enableFullBleed\",false,\"showBorder\",true,\"hidden\",false,\"showHeader\",true,\"hoistFetching\",false,\"margin\",\"4px 8px\",\"views\",[],\"showInEditor\",false,\"tooltipText\",\"\",\"padding\",\"12px\",\"_justify\",\"start\",\"style\",[\"^1J\",[\"border\",\"surfacePrimaryBorder\",\"borderRadius\",\"8px\"]],\"hiddenByIndex\",[],\"_hiddenByIndex\",[\"^A\",[\"\"]],\"currentViewIndex\",null,\"_hasMigratedNestedItems\",true,\"transition\",\"none\",\"showHeaderBorder\",true,\"footerPadding\",\"4px 12px\",\"itemMode\",\"static\",\"_gap\",\"\",\"_tooltipByIndex\",[\"^A\",[\"\"]],\"tooltipByIndex\",[],\"showFooter\",false,\"_viewKeys\",[\"^A\",[\"View 1\"]],\"_type\",\"grid\",\"events\",[\"^15\",[]],\"_ids\",[\"^A\",[\"00030\"]],\"viewKeys\",[],\"iconPositionByIndex\",[],\"_iconPositionByIndex\",[\"^A\",[\"\"]],\"hovered\",false,\"loading\",false,\"overflowType\",\"scroll\",\"disabled\",false,\"_labels\",[\"^A\",[\"\"]],\"disabledByIndex\",[],\"maintainSpaceWhenHidden\",false,\"showBody\",true,\"labels\",[]]],\"^1>\",[\"^1J\",[]],\"^1?\",[\"^0\",[\"^ \",\"n\",\"position2\",\"v\",[\"^ \",\"^18\",\"grid\",\"^1C\",\"\",\"^1K\",\"body\",\"^1L\",\"\",\"row\",166.59999999999997,\"col\",2,\"^1M\",48.39999999999999,\"^1N\",6,\"^1O\",0,\"^1P\",[\"^ \",\"^1Q\",0,\"^1R\",\"fixed\",\"^1N\",0,\"^1M\",0]]]],\"^1@\",null,\"^1A\",null,\"^1B\",null,\"^1C\",\"\",\"^7\",\"~m1769887553646\",\"^1D\",\"~m1769887572950\",\"^1E\",\"\",\"^1F\",null,\"^1G\",\"page1\",\"^1H\",null,\"^1I\",null]]],\"generateSQLButton\",[\"^0\",[\"^ \",\"n\",\"pluginTemplate\",\"v\",[\"^ \",\"id\",\"generateSQLButton\",\"^16\",\"15b29464-0fba-4284-ad42-0c37d3d66bda\",\"^17\",null,\"^18\",\"widget\",\"^19\",\"ButtonWidget2\",\"^1:\",null,\"^1;\",null,\"^1<\",null,\"^1=\",[\"^1J\",[\"heightType\",\"fixed\",\"horizontalAlign\",\"stretch\",\"clickable\",false,\"iconAfter\",\"\",\"submitTargetId\",null,\"hidden\",false,\"ariaLabel\",\"\",\"text\",\"Generate SQL\",\"margin\",\"4px 8px\",\"showInEditor\",false,\"tooltipText\",\"\",\"allowWrap\",true,\"styleVariant\",\"solid\",\"submit\",false,\"iconBefore\",\"\",\"events\",[\"^15\",[]],\"loading\",false,\"loaderPosition\",\"auto\",\"disabled\",false,\"maintainSpaceWhenHidden\",false]],\"^1>\",[\"^1J\",[]],\"^1?\",[\"^0\",[\"^ \",\"n\",\"position2\",\"v\",[\"^ \",\"^18\",\"grid\",\"^1C\",\"centerQueryContainer\",\"^1K\",\"body\",\"^1L\",\"00030\",\"row\",2.6,\"col\",0,\"^1M\",1,\"^1N\",3,\"^1O\",0,\"^1P\",[\"^ \",\"^1Q\",2,\"^1R\",\"fixed\",\"^1N\",0,\"^1M\",0]]]],\"^1@\",null,\"^1A\",null,\"^1B\",null,\"^1C\",\"\",\"^7\",\"~m1769887554002\",\"^1D\",\"~m1769887555813\",\"^1E\",\"\",\"^1F\",null,\"^1G\",\"page1\",\"^1H\",null,\"^1I\",null]]],\"explanationText\",[\"^0\",[\"^ \",\"n\",\"pluginTemplate\",\"v\",[\"^ \",\"id\",\"explanationText\",\"^16\",\"3eab118e-019c-41d2-9080-0951c4ff4c8a\",\"^17\",null,\"^18\",\"widget\",\"^19\",\"TextWidget2\",\"^1:\",null,\"^1;\",null,\"^1<\",null,\"^1=\",[\"^1J\",[\"heightType\",\"auto\",\"horizontalAlign\",\"left\",\"hidden\",false,\"imageWidth\",\"fit\",\"margin\",\"4px 8px\",\"showInEditor\",false,\"verticalAlign\",\"center\",\"tooltipText\",\"\",\"value\",\"{{ sqlExplanation.value || '_SQL explanation will appear here_' }}\",\"disableMarkdown\",false,\"overflowType\",\"scroll\",\"maintainSpaceWhenHidden\",false]],\"^1>\",[\"^1J\",[]],\"^1?\",[\"^0\",[\"^ \",\"n\",\"position2\",\"v\",[\"^ \",\"^18\",\"grid\",\"^1C\",\"centerQueryContainer\",\"^1K\",\"body\",\"^1L\",\"00030\",\"row\",6.4,\"col\",0,\"^1M\",7.6,\"^1N\",12,\"^1O\",0,\"^1P\",[\"^ \",\"^1Q\",3,\"^1R\",\"fixed\",\"^1N\",0,\"^1M\",0]]]],\"^1@\",null,\"^1A\",null,\"^1B\",null,\"^1C\",\"\",\"^7\",\"~m1769887554030\",\"^1D\",\"~m1769887607764\",\"^1E\",\"\",\"^1F\",null,\"^1G\",\"page1\",\"^1H\",null,\"^1I\",null]]],\"runQueryButton\",[\"^0\",[\"^ \",\"n\",\"pluginTemplate\",\"v\",[\"^ \",\"id\",\"runQueryButton\",\"^16\",\"8667e4fc-eba8-45c8-af5a-025fbe4176ac\",\"^17\",null,\"^18\",\"widget\",\"^19\",\"ButtonWidget2\",\"^1:\",null,\"^1;\",null,\"^1<\",null,\"^1=\",[\"^1J\",[\"heightType\",\"fixed\",\"horizontalAlign\",\"stretch\",\"clickable\",false,\"iconAfter\",\"\",\"submitTargetId\",null,\"hidden\",false,\"ariaLabel\",\"\",\"text\",\"Run Query\",\"margin\",\"4px 8px\",\"showInEditor\",false,\"tooltipText\",\"\",\"allowWrap\",true,\"styleVariant\",\"solid\",\"submit\",false,\"iconBefore\",\"\",\"events\",[\"^A\",[[\"^1J\",[\"method\",\"run\",\"params\",[\"^1J\",[\"src\",\"await queryResults.trigger();\"]],\"targetId\",null,\"pluginId\",\"\",\"waitType\",\"debounce\",\"event\",\"click\",\"type\",\"script\",\"id\",\"6fa98cfb\",\"waitMs\",\"0\"]]]],\"loading\",false,\"loaderPosition\",\"auto\",\"disabled\",false,\"maintainSpaceWhenHidden\",false]],\"^1>\",[\"^1J\",[]],\"^1?\",[\"^0\",[\"^ \",\"n\",\"position2\",\"v\",[\"^ \",\"^18\",\"grid\",\"^1C\",\"centerQueryContainer\",\"^1K\",\"body\",\"^1L\",\"00030\",\"row\",7.6,\"col\",0,\"^1M\",1,\"^1N\",3,\"^1O\",0,\"^1P\",[\"^ \",\"^1Q\",4,\"^1R\",\"fixed\",\"^1N\",0,\"^1M\",0]]]],\"^1@\",null,\"^1A\",null,\"^1B\",null,\"^1C\",\"\",\"^7\",\"~m1769887554052\",\"^1D\",\"~m1769887620339\",\"^1E\",\"\",\"^1F\",null,\"^1G\",\"page1\",\"^1H\",null,\"^1I\",null]]],\"editQueryButton\",[\"^0\",[\"^ \",\"n\",\"pluginTemplate\",\"v\",[\"^ \",\"id\",\"editQueryButton\",\"^16\",\"a6760237-7398-4dec-9d75-8c8afe5921b4\",\"^17\",null,\"^18\",\"widget\",\"^19\",\"ButtonWidget2\",\"^1:\",null,\"^1;\",null,\"^1<\",null,\"^1=\",[\"^1J\",[\"heightType\",\"fixed\",\"horizontalAlign\",\"stretch\",\"clickable\",false,\"iconAfter\",\"\",\"submitTargetId\",null,\"hidden\",false,\"ariaLabel\",\"\",\"text\",\"Edit SQL\",\"margin\",\"4px 8px\",\"showInEditor\",false,\"tooltipText\",\"\",\"allowWrap\",true,\"styleVariant\",\"outline\",\"submit\",false,\"iconBefore\",\"\",\"events\",[\"^15\",[]],\"loading\",false,\"loaderPosition\",\"auto\",\"disabled\",false,\"maintainSpaceWhenHidden\",false]],\"^1>\",[\"^1J\",[]],\"^1?\",[\"^0\",[\"^ \",\"n\",\"position2\",\"v\",[\"^ \",\"^18\",\"grid\",\"^1C\",\"centerQueryContainer\",\"^1K\",\"body\",\"^1L\",\"00030\",\"row\",7.6,\"col\",4,\"^1M\",1,\"^1N\",3,\"^1O\",0,\"^1P\",[\"^ \",\"^1Q\",5,\"^1R\",\"fixed\",\"^1N\",0,\"^1M\",0]]]],\"^1@\",null,\"^1A\",null,\"^1B\",null,\"^1C\",\"\",\"^7\",\"~m1769887554079\",\"^1D\",\"~m1769887556213\",\"^1E\",\"\",\"^1F\",null,\"^1G\",\"page1\",\"^1H\",null,\"^1I\",null]]],\"queryBuilderTitle\",[\"^0\",[\"^ \",\"n\",\"pluginTemplate\",\"v\",[\"^ \",\"id\",\"queryBuilderTitle\",\"^16\",\"7a9033dd-3269-436b-bc5a-7a1f87fefe44\",\"^17\",null,\"^18\",\"widget\",\"^19\",\"TextWidget2\",\"^1:\",null,\"^1;\",null,\"^1<\",null,\"^1=\",[\"^1J\",[\"heightType\",\"auto\",\"horizontalAlign\",\"left\",\"hidden\",false,\"imageWidth\",\"fit\",\"margin\",\"4px 8px\",\"showInEditor\",false,\"verticalAlign\",\"center\",\"tooltipText\",\"\",\"value\",\"### Query Builder\",\"disableMarkdown\",false,\"overflowType\",\"scroll\",\"maintainSpaceWhenHidden\",false]],\"^1>\",[\"^1J\",[]],\"^1?\",[\"^0\",[\"^ \",\"n\",\"position2\",\"v\",[\"^ \",\"^18\",\"grid\",\"^1C\",\"centerQueryContainer\",\"^1K\",\"header\",\"^1L\",\"00030\",\"row\",0,\"col\",0,\"^1M\",2.4,\"^1N\",12,\"^1O\",0,\"^1P\",null]]],\"^1@\",null,\"^1A\",null,\"^1B\",null,\"^1C\",\"\",\"^7\",\"~m1769887554244\",\"^1D\",\"~m1769887556011\",\"^1E\",\"\",\"^1F\",null,\"^1G\",\"page1\",\"^1H\",null,\"^1I\",null]]],\"naturalLanguageInput\",[\"^0\",[\"^ \",\"n\",\"pluginTemplate\",\"v\",[\"^ \",\"id\",\"naturalLanguageInput\",\"^16\",\"a692e3ca-1446-45ce-9300-3f1411207b9c\",\"^17\",null,\"^18\",\"widget\",\"^19\",\"TextAreaWidget\",\"^1:\",null,\"^1;\",null,\"^1<\",null,\"^1=\",[\"^1J\",[\"spellCheck\",false,\"readOnly\",false,\"autoResize\",true,\"showCharacterCount\",false,\"autoComplete\",false,\"enforceMaxLength\",false,\"maxLength\",null,\"hidden\",false,\"customValidation\",\"\",\"hideValidationMessage\",false,\"minLines\",2,\"validationMessage\",\"\",\"margin\",\"4px 8px\",\"showInEditor\",false,\"pattern\",\"\",\"tooltipText\",\"\",\"labelAlign\",\"left\",\"formDataKey\",\"{{ self.id }}\",\"value\",\"\",\"labelCaption\",\"\",\"labelWidth\",\"33\",\"autoFill\",\"\",\"placeholder\",\"Enter value\",\"label\",\"Enter your query in natural language...\",\"_validate\",false,\"labelWidthUnit\",\"%\",\"invalid\",false,\"minLength\",null,\"inputTooltip\",\"\",\"events\",[\"^15\",[]],\"autoCapitalize\",\"none\",\"maxLines\",null,\"loading\",false,\"disabled\",false,\"labelPosition\",\"top\",\"labelWrap\",false,\"maintainSpaceWhenHidden\",false,\"required\",false]],\"^1>\",[\"^1J\",[]],\"^1?\",[\"^0\",[\"^ \",\"n\",\"position2\",\"v\",[\"^ \",\"^18\",\"grid\",\"^1C\",\"centerQueryContainer\",\"^1K\",\"body\",\"^1L\",\"00030\",\"row\",0,\"col\",0,\"^1M\",3.3999999999999995,\"^1N\",12,\"^1O\",0,\"^1P\",[\"^ \",\"^1Q\",0,\"^1R\",\"fixed\",\"^1N\",0,\"^1M\",0]]]],\"^1@\",null,\"^1A\",null,\"^1B\",null,\"^1C\",\"\",\"^7\",\"~m1769887554524\",\"^1D\",\"~m1769887556240\",\"^1E\",\"\",\"^1F\",null,\"^1G\",\"page1\",\"^1H\",null,\"^1I\",null]]],\"sqlTextArea\",[\"^0\",[\"^ \",\"n\",\"pluginTemplate\",\"v\",[\"^ \",\"id\",\"sqlTextArea\",\"^16\",\"071a8e3d-8f9b-4181-96f4-85b66899d159\",\"^17\",null,\"^18\",\"widget\",\"^19\",\"TextAreaWidget\",\"^1:\",null,\"^1;\",null,\"^1<\",null,\"^1=\",[\"^1J\",[\"spellCheck\",false,\"readOnly\",false,\"autoResize\",true,\"showCharacterCount\",false,\"autoComplete\",false,\"enforceMaxLength\",false,\"maxLength\",null,\"hidden\",false,\"customValidation\",\"\",\"hideValidationMessage\",false,\"minLines\",2,\"validationMessage\",\"\",\"margin\",\"4px 8px\",\"showInEditor\",false,\"pattern\",\"\",\"tooltipText\",\"\",\"labelAlign\",\"left\",\"formDataKey\",\"{{ self.id }}\",\"value\",\"{{ currentSQL.value || 'SELECT * FROM transactions LIMIT 10;' }}\",\"labelCaption\",\"\",\"labelWidth\",\"33\",\"autoFill\",\"\",\"placeholder\",\"Enter value\",\"label\",\"Generated SQL will appear here...\",\"_validate\",false,\"labelWidthUnit\",\"%\",\"invalid\",false,\"minLength\",null,\"inputTooltip\",\"\",\"events\",[\"^15\",[]],\"autoCapitalize\",\"none\",\"maxLines\",null,\"loading\",false,\"disabled\",false,\"labelPosition\",\"top\",\"labelWrap\",false,\"maintainSpaceWhenHidden\",false,\"required\",false]],\"^1>\",[\"^1J\",[]],\"^1?\",[\"^0\",[\"^ \",\"n\",\"position2\",\"v\",[\"^ \",\"^18\",\"grid\",\"^1C\",\"centerQueryContainer\",\"^1K\",\"body\",\"^1L\",\"00030\",\"row\",4,\"col\",0,\"^1M\",7,\"^1N\",12,\"^1O\",0,\"^1P\",[\"^ \",\"^1Q\",1,\"^1R\",\"fixed\",\"^1N\",0,\"^1M\",0]]]],\"^1@\",null,\"^1A\",null,\"^1B\",null,\"^1C\",\"\",\"^7\",\"~m1769887554566\",\"^1D\",\"~m1769887607958\",\"^1E\",\"\",\"^1F\",null,\"^1G\",\"page1\",\"^1H\",null,\"^1I\",null]]],\"rightSidebarContainer\",[\"^0\",[\"^ \",\"n\",\"pluginTemplate\",\"v\",[\"^ \",\"id\",\"rightSidebarContainer\",\"^16\",\"d60d403b-9d3f-420a-b666-095c70da9c98\",\"^17\",null,\"^18\",\"widget\",\"^19\",\"ContainerWidget2\",\"^1:\",null,\"^1;\",null,\"^1<\",null,\"^1=\",[\"^1J\",[\"_direction\",\"horizontal\",\"_disabledByIndex\",[\"^A\",[\"\"]],\"heightType\",\"auto\",\"currentViewKey\",null,\"iconByIndex\",[],\"_flexWrap\",false,\"clickable\",false,\"_iconByIndex\",[\"^A\",[\"\"]],\"headerPadding\",\"4px 12px\",\"showFooterBorder\",true,\"_align\",\"start\",\"enableFullBleed\",false,\"showBorder\",true,\"hidden\",false,\"showHeader\",true,\"hoistFetching\",false,\"margin\",\"4px 8px\",\"views\",[],\"showInEditor\",false,\"tooltipText\",\"\",\"padding\",\"12px\",\"_justify\",\"start\",\"style\",[\"^1J\",[\"border\",\"surfacePrimaryBorder\",\"borderRadius\",\"8px\"]],\"hiddenByIndex\",[],\"_hiddenByIndex\",[\"^A\",[\"\"]],\"currentViewIndex\",null,\"_hasMigratedNestedItems\",true,\"transition\",\"none\",\"showHeaderBorder\",true,\"footerPadding\",\"4px 12px\",\"itemMode\",\"static\",\"_gap\",\"\",\"_tooltipByIndex\",[\"^A\",[\"\"]],\"tooltipByIndex\",[],\"showFooter\",false,\"_viewKeys\",[\"^A\",[\"View 1\"]],\"_type\",\"grid\",\"events\",[\"^15\",[]],\"_ids\",[\"^A\",[\"00030\"]],\"viewKeys\",[],\"iconPositionByIndex\",[],\"_iconPositionByIndex\",[\"^A\",[\"\"]],\"hovered\",false,\"loading\",false,\"overflowType\",\"scroll\",\"disabled\",false,\"_labels\",[\"^A\",[\"\"]],\"disabledByIndex\",[],\"maintainSpaceWhenHidden\",false,\"showBody\",true,\"labels\",[]]],\"^1>\",[\"^1J\",[]],\"^1?\",[\"^0\",[\"^ \",\"n\",\"position2\",\"v\",[\"^ \",\"^18\",\"grid\",\"^1C\",\"\",\"^1K\",\"body\",\"^1L\",\"\",\"row\",168.00000000000006,\"col\",8,\"^1M\",49.599999999999994,\"^1N\",3,\"^1O\",0,\"^1P\",null]]],\"^1@\",null,\"^1A\",null,\"^1B\",null,\"^1C\",\"\",\"^7\",\"~m1769887559835\",\"^1D\",\"~m1769887572979\",\"^1E\",\"\",\"^1F\",null,\"^1G\",\"page1\",\"^1H\",null,\"^1I\",null]]],\"resultsContainer\",[\"^0\",[\"^ \",\"n\",\"pluginTemplate\",\"v\",[\"^ \",\"id\",\"resultsContainer\",\"^16\",\"c5f671d0-8210-404b-96a9-e4afc23110fa\",\"^17\",null,\"^18\",\"widget\",\"^19\",\"ContainerWidget2\",\"^1:\",null,\"^1;\",null,\"^1<\",null,\"^1=\",[\"^1J\",[\"_direction\",\"horizontal\",\"_disabledByIndex\",[\"^A\",[\"\"]],\"heightType\",\"auto\",\"currentViewKey\",null,\"iconByIndex\",[],\"_flexWrap\",false,\"clickable\",false,\"_iconByIndex\",[\"^A\",[\"\"]],\"headerPadding\",\"4px 12px\",\"showFooterBorder\",true,\"_align\",\"start\",\"enableFullBleed\",false,\"showBorder\",true,\"hidden\",false,\"showHeader\",true,\"hoistFetching\",false,\"margin\",\"4px 8px\",\"views\",[],\"showInEditor\",false,\"tooltipText\",\"\",\"padding\",\"12px\",\"_justify\",\"start\",\"style\",[\"^1J\",[\"border\",\"surfacePrimaryBorder\",\"borderRadius\",\"8px\"]],\"hiddenByIndex\",[],\"_hiddenByIndex\",[\"^A\",[\"\"]],\"currentViewIndex\",null,\"_hasMigratedNestedItems\",true,\"transition\",\"none\",\"showHeaderBorder\",true,\"footerPadding\",\"4px 12px\",\"itemMode\",\"static\",\"_gap\",\"\",\"_tooltipByIndex\",[\"^A\",[\"\"]],\"tooltipByIndex\",[],\"showFooter\",false,\"_viewKeys\",[\"^A\",[\"View 1\"]],\"_type\",\"grid\",\"events\",[\"^15\",[]],\"_ids\",[\"^A\",[\"00030\"]],\"viewKeys\",[],\"iconPositionByIndex\",[],\"_iconPositionByIndex\",[\"^A\",[\"\"]],\"hovered\",false,\"loading\",false,\"overflowType\",\"scroll\",\"disabled\",false,\"_labels\",[\"^A\",[\"\"]],\"disabledByIndex\",[],\"maintainSpaceWhenHidden\",false,\"showBody\",true,\"labels\",[]]],\"^1>\",[\"^1J\",[]],\"^1?\",[\"^0\",[\"^ \",\"n\",\"position2\",\"v\",[\"^ \",\"^18\",\"grid\",\"^1C\",\"\",\"^1K\",\"body\",\"^1L\",\"\",\"row\",107.19999999999996,\"col\",0,\"^1M\",24,\"^1N\",12,\"^1O\",0,\"^1P\",[\"^ \",\"^1Q\",0,\"^1R\",\"fixed\",\"^1N\",0,\"^1M\",0]]]],\"^1@\",null,\"^1A\",null,\"^1B\",null,\"^1C\",\"\",\"^7\",\"~m1769887559864\",\"^1D\",\"~m1769887573346\",\"^1E\",\"\",\"^1F\",null,\"^1G\",\"page1\",\"^1H\",null,\"^1I\",null]]],\"saveViewModal\",[\"^0\",[\"^ \",\"n\",\"pluginTemplate\",\"v\",[\"^ \",\"id\",\"saveViewModal\",\"^16\",null,\"^17\",null,\"^18\",\"frame\",\"^19\",\"ModalFrameWidget\",\"^1:\",null,\"^1;\",null,\"^1<\",null,\"^1=\",[\"^1J\",[\"size\",\"medium\",\"hideOnEscape\",true,\"overlayInteraction\",true,\"headerPadding\",\"8px 12px\",\"showFooterBorder\",true,\"enableFullBleed\",false,\"isHiddenOnDesktop\",false,\"showBorder\",true,\"hidden\",true,\"showHeader\",true,\"padding\",\"8px 12px\",\"showOverlay\",true,\"isHiddenOnMobile\",true,\"showHeaderBorder\",true,\"footerPadding\",\"8px 12px\",\"showFooter\",true,\"events\",[\"^15\",[]],\"loading\",false]],\"^1>\",[\"^1J\",[]],\"^1?\",null,\"^1@\",null,\"^1A\",null,\"^1B\",null,\"^1C\",\"\",\"^7\",\"~m1769887560196\",\"^1D\",\"~m1769887572880\",\"^1E\",\"\",\"^1F\",null,\"^1G\",\"page1\",\"^1H\",null,\"^1I\",null]]],\"refinementInstructions\",[\"^0\",[\"^ \",\"n\",\"pluginTemplate\",\"v\",[\"^ \",\"id\",\"refinementInstructions\",\"^16\",\"f8b7d7fe-76d1-4ca9-b10b-fc8a3fa06e6d\",\"^17\",null,\"^18\",\"widget\",\"^19\",\"TextWidget2\",\"^1:\",null,\"^1;\",null,\"^1<\",null,\"^1=\",[\"^1J\",[\"heightType\",\"auto\",\"horizontalAlign\",\"left\",\"hidden\",false,\"imageWidth\",\"fit\",\"margin\",\"4px 8px\",\"showInEditor\",false,\"verticalAlign\",\"center\",\"tooltipText\",\"\",\"value\",\"Refine your query by providing additional context or corrections.\",\"disableMarkdown\",false,\"overflowType\",\"scroll\",\"maintainSpaceWhenHidden\",false]],\"^1>\",[\"^1J\",[]],\"^1?\",[\"^0\",[\"^ \",\"n\",\"position2\",\"v\",[\"^ \",\"^18\",\"grid\",\"^1C\",\"rightSidebarContainer\",\"^1K\",\"body\",\"^1L\",\"00030\",\"row\",0,\"col\",0,\"^1M\",1.6,\"^1N\",12,\"^1O\",0,\"^1P\",[\"^ \",\"^1Q\",0,\"^1R\",\"fixed\",\"^1N\",0,\"^1M\",0]]]],\"^1@\",null,\"^1A\",null,\"^1B\",null,\"^1C\",\"\",\"^7\",\"~m1769887560512\",\"^1D\",\"~m1769887562727\",\"^1E\",\"\",\"^1F\",null,\"^1G\",\"page1\",\"^1H\",null,\"^1I\",null]]],\"refinementInput\",[\"^0\",[\"^ \",\"n\",\"pluginTemplate\",\"v\",[\"^ \",\"id\",\"refinementInput\",\"^16\",\"d46c591d-f735-40c8-9c09-14da82dd1eea\",\"^17\",null,\"^18\",\"widget\",\"^19\",\"TextAreaWidget\",\"^1:\",null,\"^1;\",null,\"^1<\",null,\"^1=\",[\"^1J\",[\"spellCheck\",false,\"readOnly\",false,\"autoResize\",true,\"showCharacterCount\",false,\"autoComplete\",false,\"enforceMaxLength\",false,\"maxLength\",null,\"hidden\",false,\"customValidation\",\"\",\"hideValidationMessage\",false,\"minLines\",2,\"validationMessage\",\"\",\"margin\",\"4px 8px\",\"showInEditor\",false,\"pattern\",\"\",\"tooltipText\",\"\",\"labelAlign\",\"left\",\"formDataKey\",\"{{ self.id }}\",\"value\",\"\",\"labelCaption\",\"\",\"labelWidth\",\"33\",\"autoFill\",\"\",\"placeholder\",\"Enter value\",\"label\",\"Add refinement instructions...\",\"_validate\",false,\"labelWidthUnit\",\"%\",\"invalid\",false,\"minLength\",null,\"inputTooltip\",\"\",\"events\",[\"^15\",[]],\"autoCapitalize\",\"none\",\"maxLines\",null,\"loading\",false,\"disabled\",false,\"labelPosition\",\"top\",\"labelWrap\",false,\"maintainSpaceWhenHidden\",false,\"required\",false]],\"^1>\",[\"^1J\",[]],\"^1?\",[\"^0\",[\"^ \",\"n\",\"position2\",\"v\",[\"^ \",\"^18\",\"grid\",\"^1C\",\"rightSidebarContainer\",\"^1K\",\"body\",\"^1L\",\"00030\",\"row\",2,\"col\",0,\"^1M\",2.5999999999999996,\"^1N\",12,\"^1O\",0,\"^1P\",[\"^ \",\"^1Q\",1,\"^1R\",\"fixed\",\"^1N\",0,\"^1M\",0]]]],\"^1@\",null,\"^1A\",null,\"^1B\",null,\"^1C\",\"\",\"^7\",\"~m1769887560548\",\"^1D\",\"~m1769887562709\",\"^1E\",\"\",\"^1F\",null,\"^1G\",\"page1\",\"^1H\",null,\"^1I\",null]]],\"refineButton\",[\"^0\",[\"^ \",\"n\",\"pluginTemplate\",\"v\",[\"^ \",\"id\",\"refineButton\",\"^16\",\"b5a99ab2-e6cc-4f41-a684-c15ff3a090df\",\"^17\",null,\"^18\",\"widget\",\"^19\",\"ButtonWidget2\",\"^1:\",null,\"^1;\",null,\"^1<\",null,\"^1=\",[\"^1J\",[\"heightType\",\"fixed\",\"horizontalAlign\",\"stretch\",\"clickable\",false,\"iconAfter\",\"\",\"submitTargetId\",null,\"hidden\",false,\"ariaLabel\",\"\",\"text\",\"Refine Query\",\"margin\",\"4px 8px\",\"showInEditor\",false,\"tooltipText\",\"\",\"allowWrap\",true,\"styleVariant\",\"outline\",\"submit\",false,\"iconBefore\",\"\",\"events\",[\"^15\",[]],\"loading\",false,\"loaderPosition\",\"auto\",\"disabled\",false,\"maintainSpaceWhenHidden\",false]],\"^1>\",[\"^1J\",[]],\"^1?\",[\"^0\",[\"^ \",\"n\",\"position2\",\"v\",[\"^ \",\"^18\",\"grid\",\"^1C\",\"rightSidebarContainer\",\"^1K\",\"body\",\"^1L\",\"00030\",\"row\",4.6,\"col\",0,\"^1M\",1,\"^1N\",12,\"^1O\",0,\"^1P\",[\"^ \",\"^1Q\",2,\"^1R\",\"fixed\",\"^1N\",0,\"^1M\",0]]]],\"^1@\",null,\"^1A\",null,\"^1B\",null,\"^1C\",\"\",\"^7\",\"~m1769887560580\",\"^1D\",\"~m1769887563076\",\"^1E\",\"\",\"^1F\",null,\"^1G\",\"page1\",\"^1H\",null,\"^1I\",null]]],\"resultsTable\",[\"^0\",[\"^ \",\"n\",\"pluginTemplate\",\"v\",[\"^ \",\"id\",\"resultsTable\",\"^16\",\"d940cfa2-0f23-4a7b-b260-5301c9049d6a\",\"^17\",null,\"^18\",\"widget\",\"^19\",\"TableWidget2\",\"^1:\",null,\"^1;\",null,\"^1<\",null,\"^1=\",[\"^1J\",[\"selectedRowKey\",null,\"_nextAfterCursor\",\"\",\"_columnBackgroundColor\",[\"^1J\",[]],\"_defaultSort\",null,\"_columnSearchMode\",[\"^1J\",[]],\"_columnAlternateRowBackgroundColor\",[\"^1J\",[]],\"_clearChangesetOnSave\",true,\"heightType\",\"fixed\",\"_columnTextColor\",[\"^1J\",[]],\"disableEdits\",false,\"autoColumnWidth\",false,\"_rowHeight\",\"\",\"_columnIds\",[\"^A\",[]],\"_isSaving\",false,\"_headerTextWrap\",false,\"_actionIds\",[\"^A\",[]],\"_clearChangeset\",false,\"caseSensitiveFiltering\",false,\"_limitOffsetRowCount\",null,\"selectedSourceRow\",null,\"_dynamicColumnsEnabled\",false,\"disableSave\",false,\"_columnEditableOptions\",[\"^1J\",[]],\"_toolbarPosition\",\"bottom\",\"_groupByColumns\",[\"^A\",[]],\"_toolbarButtonLabel\",[\"^1J\",[\"1a\",\"Filter\",\"3c\",\"Download\",\"4d\",\"Refresh\"]],\"_nextBeforeCursor\",\"\",\"_persistRowSelection\",false,\"_toolbarButtonIcon\",[\"^1J\",[\"1a\",\"bold/interface-text-formatting-filter-2\",\"3c\",\"bold/interface-download-button-2\",\"4d\",\"bold/interface-arrows-round-left\"]],\"changesetArray\",[],\"groupByColumns\",[],\"_toolbarButtonType\",[\"^1J\",[\"1a\",\"filter\",\"3c\",\"custom\",\"4d\",\"custom\"]],\"_columnOptionList\",[\"^1J\",[]],\"_columnValueOverride\",[\"^1J\",[]],\"_showBorder\",true,\"_templatePageSize\",null,\"_dynamicColumnProperties\",[\"^1J\",[]],\"_showHeader\",true,\"_currentPage\",0,\"overflowActionsOverlayMinWidth\",null,\"_actionsOverflowPosition\",0,\"_columnKey\",[\"^1J\",[]],\"hidden\",false,\"_toolbarButtonIds\",[\"^A\",[\"1a\",\"3c\",\"4d\"]],\"columnOrdering\",[],\"data\",\"{{ queryResults.data }}\",\"_cellSelection\",\"none\",\"_serverPaginated\",false,\"_linkedFilterId\",null,\"searchMode\",\"fuzzy\",\"_columnCellTooltip\",[\"^1J\",[]],\"_columnFormat\",[\"^1J\",[]],\"_cursorCache\",[\"^ \"],\"_calculatedPageSize\",null,\"_primaryKeyColumnId\",\"\",\"selectedDataIndex\",null,\"_columnAlignment\",[\"^1J\",[]],\"_actionIcon\",[\"^1J\",[]],\"margin\",\"4px 8px\",\"_columnTooltip\",[\"^1J\",[]],\"_columnIcon\",[\"^1J\",[]],\"_alwaysShowRowSelectionCheckboxes\",false,\"_columnCellTooltipMode\",[\"^1J\",[]],\"_pageSize\",null,\"showInEditor\",false,\"_isAddingNewRows\",false,\"selectedSourceRows\",[],\"_enableExpandableRows\",false,\"_selectMultipleRowsOnActionClick\",\"no\",\"_columnSortDisabled\",[\"^1J\",[]],\"_showSummaryRow\",false,\"filterStack\",null,\"_expandedRows\",null,\"changesetObject\",null,\"_actionDisabled\",[\"^1J\",[]],\"style\",[\"^1J\",[\"rowSeparator\",\"surfacePrimaryBorder\"]],\"_columnReferenceId\",[\"^1J\",[]],\"_dynamicColumnSource\",[],\"_rowSelection\",\"single\",\"_columnCaption\",[\"^1J\",[]],\"_dynamicColumnFormatOptions\",[\"^1J\",[]],\"_dynamicRowHeights\",false,\"_columnFormatOptions\",[\"^1J\",[]],\"_changeset\",null,\"_afterCursor\",\"\",\"_columnHeaderBackgroundColor\",[\"^1J\",[]],\"selectedRowKeys\",[],\"_columnHeaderTextColor\",[\"^1J\",[]],\"_beforeCursor\",\"\",\"_columnSummaryAggregationMode\",[\"^1J\",[]],\"searchTerm\",\"\",\"selectedRows\",[],\"_disabledVirtualization\",false,\"_expandedRowDataIndexes\",[],\"_showColumnBorders\",false,\"_columnStatusIndicatorOptions\",[\"^1J\",[]],\"overflowActionsOverlayMaxHeight\",null,\"_columnSize\",[\"^1J\",[]],\"_serverPaginationType\",\"limitOffsetBased\",\"_columnSortMode\",[\"^1J\",[]],\"_selectSingleRowsOnActionClick\",\"replace\",\"_showFooter\",true,\"_groupedColumnConfig\",[\"^1J\",[]],\"_dynamicColumnSize\",[\"^1J\",[]],\"_virtualizeStartIndex\",0,\"_toolbarButtonHidden\",[\"^1J\",[\"1a\",\"\",\"3c\",\"\",\"4d\",\"\"]],\"_defaultFilters\",[\"^1J\",[]],\"events\",[\"^A\",[[\"^1J\",[\"id\",\"b8b7815a\",\"type\",\"widget\",\"waitMs\",\"0\",\"waitType\",\"debounce\",\"event\",\"clickToolbar\",\"method\",\"exportData\",\"pluginId\",\"resultsTable\",\"targetId\",\"3c\"]],[\"^1J\",[\"id\",\"5a3d951e\",\"type\",\"widget\",\"waitMs\",\"0\",\"waitType\",\"debounce\",\"event\",\"clickToolbar\",\"method\",\"refresh\",\"pluginId\",\"resultsTable\",\"targetId\",\"4d\"]]]],\"_columnEditable\",[\"^1J\",[]],\"newRows\",[],\"_rowBackgroundColor\",[],\"emptyMessage\",\"No rows found\",\"pagination\",null,\"selectedDataIndexes\",[],\"_columnEditableInNewRows\",[\"^1J\",[]],\"_columnGroupAggregationMode\",[\"^1J\",[]],\"sortArray\",[],\"_selectedCell\",null,\"overflowType\",\"scroll\",\"selectedCell\",null,\"_defaultSelectedRow\",[\"^1J\",[\"mode\",\"none\",\"indexType\",\"display\",\"index\",0]],\"_hasNextPage\",false,\"_includeRowInChangesetArray\",false,\"_columnPosition\",[\"^1J\",[]],\"_enableSaveActions\",true,\"_columnPlaceholder\",[\"^1J\",[]],\"_defaultFilterOperator\",\"and\",\"_actionLabel\",[\"^1J\",[]],\"_virtualizeEndIndex\",0,\"selectedRow\",null,\"_actionHidden\",[\"^1J\",[]],\"maintainSpaceWhenHidden\",false,\"_columnHidden\",[\"^1J\",[]],\"_columnLabel\",[\"^1J\",[]],\"_showToolbar\",true]],\"^1>\",[\"^1J\",[]],\"^1?\",[\"^0\",[\"^ \",\"n\",\"position2\",\"v\",[\"^ \",\"^18\",\"grid\",\"^1C\",\"resultsContainer\",\"^1K\",\"body\",\"^1L\",\"00030\",\"row\",0,\"col\",0,\"^1M\",12,\"^1N\",12,\"^1O\",0,\"^1P\",[\"^ \",\"^1Q\",0,\"^1R\",\"fixed\",\"^1N\",0,\"^1M\",0]]]],\"^1@\",null,\"^1A\",null,\"^1B\",null,\"^1C\",\"\",\"^7\",\"~m1769887560647\",\"^1D\",\"~m1769887597104\",\"^1E\",\"\",\"^1F\",null,\"^1G\",\"page1\",\"^1H\",null,\"^1I\",null]]],\"saveViewModalTitle\",[\"^0\",[\"^ \",\"n\",\"pluginTemplate\",\"v\",[\"^ \",\"id\",\"saveViewModalTitle\",\"^16\",\"0112b45c-4320-4c74-ab76-b4791b604053\",\"^17\",null,\"^18\",\"widget\",\"^19\",\"TextWidget2\",\"^1:\",null,\"^1;\",null,\"^1<\",null,\"^1=\",[\"^1J\",[\"heightType\",\"auto\",\"horizontalAlign\",\"left\",\"hidden\",false,\"imageWidth\",\"fit\",\"margin\",\"4px 8px\",\"showInEditor\",false,\"verticalAlign\",\"center\",\"tooltipText\",\"\",\"value\",\"### Save View\",\"disableMarkdown\",false,\"overflowType\",\"scroll\",\"maintainSpaceWhenHidden\",false]],\"^1>\",[\"^1J\",[]],\"^1?\",[\"^0\",[\"^ \",\"n\",\"position2\",\"v\",[\"^ \",\"^18\",\"grid\",\"^1C\",\"\",\"^1K\",\"header\",\"^1L\",\"saveViewModal\",\"row\",0,\"col\",0,\"^1M\",3.6,\"^1N\",12,\"^1O\",0,\"^1P\",null]]],\"^1@\",null,\"^1A\",null,\"^1B\",null,\"^1C\",\"\",\"^7\",\"~m1769887560879\",\"^1D\",\"~m1769887562761\",\"^1E\",\"\",\"^1F\",null,\"^1G\",\"page1\",\"^1H\",null,\"^1I\",null]]],\"aiRefinementTitle\",[\"^0\",[\"^ \",\"n\",\"pluginTemplate\",\"v\",[\"^ \",\"id\",\"aiRefinementTitle\",\"^16\",\"82dfaa55-f9ba-4e90-84a8-b8ce9bf14e73\",\"^17\",null,\"^18\",\"widget\",\"^19\",\"TextWidget2\",\"^1:\",null,\"^1;\",null,\"^1<\",null,\"^1=\",[\"^1J\",[\"heightType\",\"auto\",\"horizontalAlign\",\"left\",\"hidden\",false,\"imageWidth\",\"fit\",\"margin\",\"4px 8px\",\"showInEditor\",false,\"verticalAlign\",\"center\",\"tooltipText\",\"\",\"value\",\"### AI Refinement\",\"disableMarkdown\",false,\"overflowType\",\"scroll\",\"maintainSpaceWhenHidden\",false]],\"^1>\",[\"^1J\",[]],\"^1?\",[\"^0\",[\"^ \",\"n\",\"position2\",\"v\",[\"^ \",\"^18\",\"grid\",\"^1C\",\"rightSidebarContainer\",\"^1K\",\"header\",\"^1L\",\"00030\",\"row\",0,\"col\",0,\"^1M\",1.9999999999999998,\"^1N\",12,\"^1O\",0,\"^1P\",null]]],\"^1@\",null,\"^1A\",null,\"^1B\",null,\"^1C\",\"\",\"^7\",\"~m1769887560929\",\"^1D\",\"~m1769887562803\",\"^1E\",\"\",\"^1F\",null,\"^1G\",\"page1\",\"^1H\",null,\"^1I\",null]]],\"resultsTitle\",[\"^0\",[\"^ \",\"n\",\"pluginTemplate\",\"v\",[\"^ \",\"id\",\"resultsTitle\",\"^16\",\"e2262fb8-1a49-47ae-8dec-7a22358cf7ca\",\"^17\",null,\"^18\",\"widget\",\"^19\",\"TextWidget2\",\"^1:\",null,\"^1;\",null,\"^1<\",null,\"^1=\",[\"^1J\",[\"heightType\",\"auto\",\"horizontalAlign\",\"left\",\"hidden\",false,\"imageWidth\",\"fit\",\"margin\",\"4px 8px\",\"showInEditor\",false,\"verticalAlign\",\"center\",\"tooltipText\",\"\",\"value\",\"### Results\",\"disableMarkdown\",false,\"overflowType\",\"scroll\",\"maintainSpaceWhenHidden\",false]],\"^1>\",[\"^1J\",[]],\"^1?\",[\"^0\",[\"^ \",\"n\",\"position2\",\"v\",[\"^ \",\"^18\",\"grid\",\"^1C\",\"resultsContainer\",\"^1K\",\"header\",\"^1L\",\"00030\",\"row\",0,\"col\",0,\"^1M\",1.9999999999999998,\"^1N\",8,\"^1O\",0,\"^1P\",null]]],\"^1@\",null,\"^1A\",null,\"^1B\",null,\"^1C\",\"\",\"^7\",\"~m1769887560970\",\"^1D\",\"~m1769887562746\",\"^1E\",\"\",\"^1F\",null,\"^1G\",\"page1\",\"^1H\",null,\"^1I\",null]]],\"rowCountText\",[\"^0\",[\"^ \",\"n\",\"pluginTemplate\",\"v\",[\"^ \",\"id\",\"rowCountText\",\"^16\",\"a19872af-fd8e-4201-b7fe-7f6d64707f4a\",\"^17\",null,\"^18\",\"widget\",\"^19\",\"TextWidget2\",\"^1:\",null,\"^1;\",null,\"^1<\",null,\"^1=\",[\"^1J\",[\"heightType\",\"auto\",\"horizontalAlign\",\"left\",\"hidden\",false,\"imageWidth\",\"fit\",\"margin\",\"4px 8px\",\"showInEditor\",false,\"verticalAlign\",\"center\",\"tooltipText\",\"\",\"value\",\"**Rows:** {{ (queryResults.data || []).length }}\",\"disableMarkdown\",false,\"overflowType\",\"scroll\",\"maintainSpaceWhenHidden\",false]],\"^1>\",[\"^1J\",[]],\"^1?\",[\"^0\",[\"^ \",\"n\",\"position2\",\"v\",[\"^ \",\"^18\",\"grid\",\"^1C\",\"resultsContainer\",\"^1K\",\"header\",\"^1L\",\"00030\",\"row\",0,\"col\",8,\"^1M\",3.6,\"^1N\",4,\"^1O\",0,\"^1P\",null]]],\"^1@\",null,\"^1A\",null,\"^1B\",null,\"^1C\",\"\",\"^7\",\"~m1769887561009\",\"^1D\",\"~m1769887607907\",\"^1E\",\"\",\"^1F\",null,\"^1G\",\"page1\",\"^1H\",null,\"^1I\",null]]],\"viewDescriptionInput\",[\"^0\",[\"^ \",\"n\",\"pluginTemplate\",\"v\",[\"^ \",\"id\",\"viewDescriptionInput\",\"^16\",\"3fb040ea-68e8-420e-bdfb-ce01f828cb37\",\"^17\",null,\"^18\",\"widget\",\"^19\",\"TextAreaWidget\",\"^1:\",null,\"^1;\",null,\"^1<\",null,\"^1=\",[\"^1J\",[\"spellCheck\",false,\"readOnly\",false,\"autoResize\",true,\"showCharacterCount\",false,\"autoComplete\",false,\"enforceMaxLength\",false,\"maxLength\",null,\"hidden\",false,\"customValidation\",\"\",\"hideValidationMessage\",false,\"minLines\",2,\"validationMessage\",\"\",\"margin\",\"4px 8px\",\"showInEditor\",false,\"pattern\",\"\",\"tooltipText\",\"\",\"labelAlign\",\"left\",\"formDataKey\",\"{{ self.id }}\",\"value\",\"\",\"labelCaption\",\"\",\"labelWidth\",\"33\",\"autoFill\",\"\",\"placeholder\",\"Enter value\",\"label\",\"Description (optional)\",\"_validate\",false,\"labelWidthUnit\",\"%\",\"invalid\",false,\"minLength\",null,\"inputTooltip\",\"\",\"events\",[\"^15\",[]],\"autoCapitalize\",\"none\",\"maxLines\",null,\"loading\",false,\"disabled\",false,\"labelPosition\",\"top\",\"labelWrap\",false,\"maintainSpaceWhenHidden\",false,\"required\",false]],\"^1>\",[\"^1J\",[]],\"^1?\",[\"^0\",[\"^ \",\"n\",\"position2\",\"v\",[\"^ \",\"^18\",\"grid\",\"^1C\",\"\",\"^1K\",\"body\",\"^1L\",\"saveViewModal\",\"row\",0.6000000000000001,\"col\",0,\"^1M\",3.8,\"^1N\",12,\"^1O\",0,\"^1P\",null]]],\"^1@\",null,\"^1A\",null,\"^1B\",null,\"^1C\",\"\",\"^7\",\"~m1769887568528\",\"^1D\",\"~m1769887569839\",\"^1E\",\"\",\"^1F\",null,\"^1G\",\"page1\",\"^1H\",null,\"^1I\",null]]],\"cancelSaveButton\",[\"^0\",[\"^ \",\"n\",\"pluginTemplate\",\"v\",[\"^ \",\"id\",\"cancelSaveButton\",\"^16\",\"d04019a5-dfad-4dfa-a53b-1d4db59b6a38\",\"^17\",null,\"^18\",\"widget\",\"^19\",\"ButtonWidget2\",\"^1:\",null,\"^1;\",null,\"^1<\",null,\"^1=\",[\"^1J\",[\"heightType\",\"fixed\",\"horizontalAlign\",\"stretch\",\"clickable\",false,\"iconAfter\",\"\",\"submitTargetId\",null,\"hidden\",false,\"ariaLabel\",\"\",\"text\",\"Cancel\",\"margin\",\"4px 8px\",\"showInEditor\",false,\"tooltipText\",\"\",\"allowWrap\",true,\"styleVariant\",\"outline\",\"submit\",false,\"iconBefore\",\"\",\"events\",[\"^A\",[[\"^1J\",[\"method\",\"run\",\"params\",[\"^1J\",[\"src\",\"saveViewModal.hide();\"]],\"targetId\",null,\"pluginId\",\"\",\"waitType\",\"debounce\",\"event\",\"click\",\"type\",\"script\",\"id\",\"6cde09c1\",\"waitMs\",\"0\"]]]],\"loading\",false,\"loaderPosition\",\"auto\",\"disabled\",false,\"maintainSpaceWhenHidden\",false]],\"^1>\",[\"^1J\",[]],\"^1?\",[\"^0\",[\"^ \",\"n\",\"position2\",\"v\",[\"^ \",\"^18\",\"grid\",\"^1C\",\"\",\"^1K\",\"footer\",\"^1L\",\"saveViewModal\",\"row\",0,\"col\",0,\"^1M\",1,\"^1N\",4,\"^1O\",0,\"^1P\",null]]],\"^1@\",null,\"^1A\",null,\"^1B\",null,\"^1C\",\"\",\"^7\",\"~m1769887568670\",\"^1D\",\"~m1769887624783\",\"^1E\",\"\",\"^1F\",null,\"^1G\",\"page1\",\"^1H\",null,\"^1I\",null]]],\"saveViewSubmitButton\",[\"^0\",[\"^ \",\"n\",\"pluginTemplate\",\"v\",[\"^ \",\"id\",\"saveViewSubmitButton\",\"^16\",\"1e96693f-baa3-4e09-990e-a696dc57daed\",\"^17\",null,\"^18\",\"widget\",\"^19\",\"ButtonWidget2\",\"^1:\",null,\"^1;\",null,\"^1<\",null,\"^1=\",[\"^1J\",[\"heightType\",\"fixed\",\"horizontalAlign\",\"stretch\",\"clickable\",false,\"iconAfter\",\"\",\"submitTargetId\",null,\"hidden\",false,\"ariaLabel\",\"\",\"text\",\"Save\",\"margin\",\"4px 8px\",\"showInEditor\",false,\"tooltipText\",\"\",\"allowWrap\",true,\"styleVariant\",\"solid\",\"submit\",false,\"iconBefore\",\"\",\"events\",[\"^15\",[]],\"loading\",false,\"loaderPosition\",\"auto\",\"disabled\",false,\"maintainSpaceWhenHidden\",false]],\"^1>\",[\"^1J\",[]],\"^1?\",[\"^0\",[\"^ \",\"n\",\"position2\",\"v\",[\"^ \",\"^18\",\"grid\",\"^1C\",\"\",\"^1K\",\"footer\",\"^1L\",\"saveViewModal\",\"row\",0,\"col\",8,\"^1M\",1,\"^1N\",4,\"^1O\",0,\"^1P\",null]]],\"^1@\",null,\"^1A\",null,\"^1B\",null,\"^1C\",\"\",\"^7\",\"~m1769887568719\",\"^1D\",\"~m1769887570079\",\"^1E\",\"\",\"^1F\",null,\"^1G\",\"page1\",\"^1H\",null,\"^1I\",null]]],\"viewNameInput\",[\"^0\",[\"^ \",\"n\",\"pluginTemplate\",\"v\",[\"^ \",\"id\",\"viewNameInput\",\"^16\",\"d273b637-e059-45af-a89b-7b48b9fac787\",\"^17\",null,\"^18\",\"widget\",\"^19\",\"TextInputWidget2\",\"^1:\",null,\"^1;\",null,\"^1<\",null,\"^1=\",[\"^1J\",[\"spellCheck\",false,\"readOnly\",false,\"iconAfter\",\"\",\"showCharacterCount\",false,\"autoComplete\",false,\"enforceMaxLength\",false,\"maxLength\",null,\"hidden\",false,\"customValidation\",\"\",\"patternType\",\"\",\"hideValidationMessage\",false,\"textBefore\",\"\",\"validationMessage\",\"\",\"margin\",\"4px 8px\",\"textAfter\",\"\",\"showInEditor\",false,\"showClear\",false,\"pattern\",\"\",\"tooltipText\",\"\",\"labelAlign\",\"left\",\"formDataKey\",\"{{ self.id }}\",\"value\",\"\",\"labelCaption\",\"\",\"labelWidth\",\"33\",\"autoFill\",\"\",\"placeholder\",\"Enter value\",\"label\",\"View Name\",\"_validate\",false,\"labelWidthUnit\",\"%\",\"invalid\",false,\"iconBefore\",\"\",\"minLength\",null,\"inputTooltip\",\"\",\"events\",[\"^15\",[]],\"autoCapitalize\",\"none\",\"loading\",false,\"disabled\",false,\"labelPosition\",\"top\",\"labelWrap\",false,\"maintainSpaceWhenHidden\",false,\"required\",false]],\"^1>\",[\"^1J\",[]],\"^1?\",[\"^0\",[\"^ \",\"n\",\"position2\",\"v\",[\"^ \",\"^18\",\"grid\",\"^1C\",\"\",\"^1K\",\"body\",\"^1L\",\"saveViewModal\",\"row\",0,\"col\",0,\"^1M\",3,\"^1N\",12,\"^1O\",0,\"^1P\",null]]],\"^1@\",null,\"^1A\",null,\"^1B\",null,\"^1C\",\"\",\"^7\",\"~m1769887568925\",\"^1D\",\"~m1769887570201\",\"^1E\",\"\",\"^1F\",null,\"^1G\",\"page1\",\"^1H\",null,\"^1I\",null]]]]],\"preloadedAppJavaScript\",null,\"preloadedAppJSLinks\",[],\"queryStatusVisibility\",false,\"responsiveLayoutDisabled\",false,\"rootScreen\",\"page1\",\"savePlatform\",\"web\",\"shortlink\",null,\"testEntities\",[],\"tests\",[],\"urlFragmentDefinitions\",[\"^A\",[]],\"version\",\"3.333.0\",\"serializedLayout\",null,\"agentEvals\",[\"^ \"]]]]"},"changesRecord":[],"changesRecordV2":[],"checksum":null,"multiplayerSessionId":null,"appTestingSaveId":null,"subflows":null,"isCopilotGenerated":false,"createdAt":"2026-01-31T21:38:16.400Z","updatedAt":"2026-01-31T21:38:16.400Z","pageId":4833440,"userId":null},"modules":{}}